{
  "tags": [],
  "isnis": [
    "0000000083520423"
  ],
  "begin-area": {
    "name": "Ceuta",
    "iso-3166-2-codes": [
      "ES-CE"
    ],
    "id": "381524a3-718f-4a22-837e-e3bc698a45ef",
    "sort-name": "Ceuta",
    "disambiguation": "",
    "type-id": null,
    "type": null
  },
  "ipis": [
    "00069790427"
  ],
  "gender-id": "36d3d30a-839d-3eda-8cb3-29be4384e4a9",
  "type": "Person",
  "genres": [],
  "life-span": {
    "ended": true,
    "begin": "1948-07-21",
    "end": "2015-05-19"
  },
  "name": "Manuel Molina",
  "country": "ES",
  "end-area": {
    "name": "San Juan de Aznalfarache",
    "type": null,
    "type-id": null,
    "id": "0adc4677-6f7f-4776-be7f-931b014e69f4",
    "sort-name": "San Juan de Aznalfarache",
    "disambiguation": ""
  },
  "relations": [
    {
      "type": "married",
      "attribute-ids": {},
      "attribute-values": {},
      "source-credit": "",
      "end": null,
      "ended": false,
      "direction": "backward",
      "attributes": [],
      "artist": {
        "name": "Lole Montoya",
        "country": "ES",
        "sort-name": "Montoya, Lole",
        "disambiguation": "",
        "id": "50aa583a-3960-49dd-b1a8-67f62e4dea2c",
        "type": "Person",
        "type-id": "b6e035f4-3ce9-331c-97df-83397230b0df"
      },
      "begin": null,
      "type-id": "b2bf7a5d-2da6-4742-baf4-e38d8a7ad029",
      "target-credit": "Dolores Montoya",
      "target-type": "artist"
    },
    {
      "artist": {
        "type": "Group",
        "type-id": "e431f5f6-b5d2-343d-8b36-72607fffb74b",
        "sort-name": "Smash",
        "disambiguation": "Spanish prog",
        "id": "6f00fe08-50fc-4b22-a5fb-2e422fb675f3",
        "name": "Smash",
        "country": "ES"
      },
      "attributes": [],
      "direction": "forward",
      "ended": true,
      "source-credit": "",
      "end": "1972",
      "attribute-ids": {},
      "attribute-values": {},
      "type": "member of band",
      "target-type": "artist",
      "target-credit": "",
      "type-id": "5be4c609-9afa-4ea0-910b-12ffb71e3821",
      "begin": "1971"
    },
    {
      "target-credit": "",
      "type-id": "5be4c609-9afa-4ea0-910b-12ffb71e3821",
      "begin": null,
      "target-type": "artist",
      "source-credit": "",
      "end": null,
      "attribute-ids": {},
      "attribute-values": {},
      "type": "member of band",
      "artist": {
        "id": "863de8b5-4283-48f4-84fa-330cd073f84a",
        "sort-name": "Lole y Manuel",
        "disambiguation": "",
        "type-id": "e431f5f6-b5d2-343d-8b36-72607fffb74b",
        "type": "Group",
        "country": "ES",
        "name": "Lole y Manuel"
      },
      "attributes": [],
      "direction": "forward",
      "ended": false
    },
    {
      "type": "parent",
      "source-credit": "",
      "end": null,
      "attribute-values": {},
      "attribute-ids": {},
      "direction": "forward",
      "ended": false,
      "artist": {
        "country": "ES",
        "name": "Alba Molina",
        "type": "Person",
        "type-id": "b6e035f4-3ce9-331c-97df-83397230b0df",
        "id": "17397bbf-fa44-4cc9-982d-e5d9d1e32a42",
        "disambiguation": "",
        "sort-name": "Molina, Alba"
      },
      "attributes": [],
      "type-id": "9421ca84-934f-49fe-9e66-dea242430406",
      "begin": null,
      "target-credit": "",
      "target-type": "artist"
    }
  ],
  "sort-name": "Molina, Manuel",
  "disambiguation": "Spanish flamenco composer and singer",
  "id": "be600e96-9ce5-4fc7-8da4-a37acd57654d",
  "area": {
    "name": "Spain",
    "iso-3166-1-codes": [
      "ES"
    ],
    "id": "471c46a7-afc5-31c4-923c-d0444f5053a4",
    "disambiguation": "",
    "sort-name": "Spain",
    "type-id": null,
    "type": null
  },
  "type-id": "b6e035f4-3ce9-331c-97df-83397230b0df",
  "gender": "Male"
}