{
  "created": "2026-05-18T06:36:19.307Z",
  "count": 22,
  "offset": 0,
  "recordings": [
    {
      "id": "33f0414b-f453-4524-9cf0-81f5087b9fc5",
      "score": 100,
      "artist-credit-id": "7403167d-416b-3dee-96c6-4725d8c3eed3",
      "title": "Low Man's Lyric",
      "length": 437293,
      "video": null,
      "artist-credit": [
        {
          "name": "Metallica",
          "artist": {
            "id": "65f4f0c5-ef9e-490c-aee3-909e7ae6b2ab",
            "name": "Metallica",
            "sort-name": "Metallica",
            "aliases": [
              {
                "sort-name": "\u30e1\u30bf\u30ea\u30ab",
                "type-id": "894afba6-2816-3c24-8072-eadb66bd04bc",
                "name": "\u30e1\u30bf\u30ea\u30ab",
                "locale": "ja",
                "type": "Artist name",
                "primary": true,
                "begin-date": null,
                "end-date": null
              },
              {
                "sort-name": "Metalica",
                "type-id": "1937e404-b981-3cb7-8151-4c86ebfc8d8e",
                "name": "Metalica",
                "locale": null,
                "type": "Search hint",
                "primary": null,
                "begin-date": null,
                "end-date": null
              },
              {
                "sort-name": "\uba54\ud0c8\ub9ac\uce74",
                "name": "\uba54\ud0c8\ub9ac\uce74",
                "locale": "ko_KR",
                "type": null,
                "primary": true,
                "begin-date": null,
                "end-date": null
              },
              {
                "sort-name": "Metallica",
                "type-id": "894afba6-2816-3c24-8072-eadb66bd04bc",
                "name": "Metallica",
                "locale": "en",
                "type": "Artist name",
                "primary": true,
                "begin-date": null,
                "end-date": null
              }
            ]
          }
        }
      ],
      "first-release-date": "2006",
      "releases": [
        {
          "id": "db76d47d-ef63-46b4-bc01-74d7f54a4b88",
          "status-id": "1156806e-d06a-38bd-83f0-cf2284a808b9",
          "artist-credit-id": "7403167d-416b-3dee-96c6-4725d8c3eed3",
          "count": 1,
          "title": "The Golden Unplugged Album",
          "status": "Bootleg",
          "artist-credit": [
            {
              "name": "Metallica",
              "artist": {
                "id": "65f4f0c5-ef9e-490c-aee3-909e7ae6b2ab",
                "name": "Metallica",
                "sort-name": "Metallica"
              }
            }
          ],
          "release-group": {
            "id": "065a6793-3676-3f76-ada7-476efde321f2",
            "type-id": "dd2a21e1-0c00-3729-a7a0-de60b84eb5d1",
            "primary-type-id": "f529b476-6e62-324f-b0aa-1f3e33d313fc",
            "title": "The Golden Unplugged Album",
            "primary-type": "Album",
            "secondary-types": [
              "Compilation"
            ],
            "secondary-type-ids": [
              "dd2a21e1-0c00-3729-a7a0-de60b84eb5d1"
            ]
          },
          "track-count": 13,
          "media": [
            {
              "id": "611482a7-a8bb-3800-8052-4344a8cfaf3a",
              "position": 1,
              "track": [
                {
                  "id": "437507fe-a1e2-388f-b210-f01483a9ca3b",
                  "number": "2",
                  "title": "Low Man's Lyric",
                  "length": 437293
                }
              ],
              "track-count": 13,
              "track-offset": 1
            }
          ]
        }
      ],
      "tags": [
        {
          "count": 1,
          "name": "heavy metal"
        },
        {
          "count": 1,
          "name": "thrash metal"
        },
        {
          "count": 2,
          "name": "metal"
        },
        {
          "count": 1,
          "name": "hard rock"
        },
        {
          "count": 1,
          "name": "thrash"
        }
      ]
    },
    {
      "id": "8d9af706-64bc-410e-a5cb-f2b82cc5d440",
      "score": 100,
      "artist-credit-id": "7403167d-416b-3dee-96c6-4725d8c3eed3",
      "title": "Low Man's Lyric",
      "length": 432955,
      "disambiguation": "live, 2024-12-13: Helping Hands Concert 2024, YouTube Theater, Inglewood, CA, USA",
      "video": null,
      "artist-credit": [
        {
          "name": "Metallica",
          "artist": {
            "id": "65f4f0c5-ef9e-490c-aee3-909e7ae6b2ab",
            "name": "Metallica",
            "sort-name": "Metallica",
            "aliases": [
              {
                "sort-name": "\u30e1\u30bf\u30ea\u30ab",
                "type-id": "894afba6-2816-3c24-8072-eadb66bd04bc",
                "name": "\u30e1\u30bf\u30ea\u30ab",
                "locale": "ja",
                "type": "Artist name",
                "primary": true,
                "begin-date": null,
                "end-date": null
              },
              {
                "sort-name": "Metalica",
                "type-id": "1937e404-b981-3cb7-8151-4c86ebfc8d8e",
                "name": "Metalica",
                "locale": null,
                "type": "Search hint",
                "primary": null,
                "begin-date": null,
                "end-date": null
              },
              {
                "sort-name": "\uba54\ud0c8\ub9ac\uce74",
                "name": "\uba54\ud0c8\ub9ac\uce74",
                "locale": "ko_KR",
                "type": null,
                "primary": true,
                "begin-date": null,
                "end-date": null
              },
              {
                "sort-name": "Metallica",
                "type-id": "894afba6-2816-3c24-8072-eadb66bd04bc",
                "name": "Metallica",
                "locale": "en",
                "type": "Artist name",
                "primary": true,
                "begin-date": null,
                "end-date": null
              }
            ]
          }
        }
      ],
      "first-release-date": "2024-12-13",
      "releases": [
        {
          "id": "d34caff2-0a48-4395-8aa0-8089623aa6d4",
          "status-id": "4e304316-386d-3409-af2e-78857eec5cfe",
          "artist-credit-id": "7403167d-416b-3dee-96c6-4725d8c3eed3",
          "count": 1,
          "title": "2024-12-13: YouTube Theater Los Angeles, CA",
          "status": "Official",
          "artist-credit": [
            {
              "name": "Metallica",
              "artist": {
                "id": "65f4f0c5-ef9e-490c-aee3-909e7ae6b2ab",
                "name": "Metallica",
                "sort-name": "Metallica"
              }
            }
          ],
          "release-group": {
            "id": "edc1e519-2754-460e-8c72-f71c04de6bbc",
            "type-id": "6fd474e2-6b58-3102-9d17-d6f7eb7da0a0",
            "primary-type-id": "f529b476-6e62-324f-b0aa-1f3e33d313fc",
            "title": "2024-12-13: YouTube Theater Los Angeles, CA",
            "primary-type": "Album",
            "secondary-types": [
              "Live"
            ],
            "secondary-type-ids": [
              "6fd474e2-6b58-3102-9d17-d6f7eb7da0a0"
            ]
          },
          "date": "2024-12-13",
          "country": "XW",
          "release-events": [
            {
              "date": "2024-12-13",
              "area": {
                "id": "525d4e18-3d00-31b9-a58b-a146a916de8f",
                "name": "[Worldwide]",
                "sort-name": "[Worldwide]",
                "iso-3166-1-codes": [
                  "XW"
                ]
              }
            }
          ],
          "track-count": 15,
          "media": [
            {
              "id": "788e564d-8d8d-318d-a831-3d3387f5ceed",
              "position": 1,
              "format": "Digital Media",
              "track": [
                {
                  "id": "d4cff11a-f006-45fb-a55c-ae7e426330c2",
                  "number": "2",
                  "title": "Low Man's Lyric",
                  "length": 432955
                }
              ],
              "track-count": 15,
              "track-offset": 1
            }
          ]
        }
      ]
    },
    {
      "id": "6ebbb132-19e9-412a-83df-aee7b222def1",
      "score": 100,
      "artist-credit-id": "7403167d-416b-3dee-96c6-4725d8c3eed3",
      "title": "Low Man\u2019s Lyric",
      "length": 439760,
      "disambiguation": "live, 1997-10-18: Acoustic Show, Canada",
      "video": null,
      "artist-credit": [
        {
          "name": "Metallica",
          "artist": {
            "id": "65f4f0c5-ef9e-490c-aee3-909e7ae6b2ab",
            "name": "Metallica",
            "sort-name": "Metallica",
            "aliases": [
              {
                "sort-name": "\u30e1\u30bf\u30ea\u30ab",
                "type-id": "894afba6-2816-3c24-8072-eadb66bd04bc",
                "name": "\u30e1\u30bf\u30ea\u30ab",
                "locale": "ja",
                "type": "Artist name",
                "primary": true,
                "begin-date": null,
                "end-date": null
              },
              {
                "sort-name": "Metalica",
                "type-id": "1937e404-b981-3cb7-8151-4c86ebfc8d8e",
                "name": "Metalica",
                "locale": null,
                "type": "Search hint",
                "primary": null,
                "begin-date": null,
                "end-date": null
              },
              {
                "sort-name": "\uba54\ud0c8\ub9ac\uce74",
                "name": "\uba54\ud0c8\ub9ac\uce74",
                "locale": "ko_KR",
                "type": null,
                "primary": true,
                "begin-date": null,
                "end-date": null
              },
              {
                "sort-name": "Metallica",
                "type-id": "894afba6-2816-3c24-8072-eadb66bd04bc",
                "name": "Metallica",
                "locale": "en",
                "type": "Artist name",
                "primary": true,
                "begin-date": null,
                "end-date": null
              }
            ]
          }
        }
      ],
      "first-release-date": "1997",
      "releases": [
        {
          "id": "082285a8-515e-38ab-b72a-f711a95ff38e",
          "status-id": "1156806e-d06a-38bd-83f0-cf2284a808b9",
          "artist-credit-id": "7403167d-416b-3dee-96c6-4725d8c3eed3",
          "count": 1,
          "title": "Acoustic Metal",
          "status": "Bootleg",
          "artist-credit": [
            {
              "name": "Metallica",
              "artist": {
                "id": "65f4f0c5-ef9e-490c-aee3-909e7ae6b2ab",
                "name": "Metallica",
                "sort-name": "Metallica"
              }
            }
          ],
          "release-group": {
            "id": "5f4e36b8-e42b-3813-9d95-542d5484fd5e",
            "type-id": "6fd474e2-6b58-3102-9d17-d6f7eb7da0a0",
            "primary-type-id": "f529b476-6e62-324f-b0aa-1f3e33d313fc",
            "title": "Acoustic Metal",
            "primary-type": "Album",
            "secondary-types": [
              "Live"
            ],
            "secondary-type-ids": [
              "6fd474e2-6b58-3102-9d17-d6f7eb7da0a0"
            ]
          },
          "date": "",
          "country": "GB",
          "release-events": [
            {
              "date": "",
              "area": {
                "id": "8a754a16-0027-3a29-b6d7-2b40ea0481ed",
                "name": "United Kingdom",
                "sort-name": "United Kingdom",
                "iso-3166-1-codes": [
                  "GB"
                ]
              }
            }
          ],
          "track-count": 11,
          "media": [
            {
              "id": "e8badb68-5ce5-3e78-8501-91d326e0e892",
              "position": 1,
              "format": "CD",
              "track": [
                {
                  "id": "a2a9b390-b156-33e9-9f62-ab24df68f632",
                  "number": "1",
                  "title": "Low Man\u2019s Lyric",
                  "length": 439760
                }
              ],
              "track-count": 11,
              "track-offset": 0
            }
          ]
        },
        {
          "id": "77ee7d6c-4ce6-4eef-98a7-5787551d9566",
          "status-id": "1156806e-d06a-38bd-83f0-cf2284a808b9",
          "artist-credit-id": "7403167d-416b-3dee-96c6-4725d8c3eed3",
          "count": 1,
          "title": "Acoustic Metal",
          "status": "Bootleg",
          "artist-credit": [
            {
              "name": "Metallica",
              "artist": {
                "id": "65f4f0c5-ef9e-490c-aee3-909e7ae6b2ab",
                "name": "Metallica",
                "sort-name": "Metallica"
              }
            }
          ],
          "release-group": {
            "id": "5f4e36b8-e42b-3813-9d95-542d5484fd5e",
            "type-id": "6fd474e2-6b58-3102-9d17-d6f7eb7da0a0",
            "primary-type-id": "f529b476-6e62-324f-b0aa-1f3e33d313fc",
            "title": "Acoustic Metal",
            "primary-type": "Album",
            "secondary-types": [
              "Live"
            ],
            "secondary-type-ids": [
              "6fd474e2-6b58-3102-9d17-d6f7eb7da0a0"
            ]
          },
          "date": "1997",
          "country": "US",
          "release-events": [
            {
              "date": "1997",
              "area": {
                "id": "489ce91b-6658-3307-9877-795b68554c98",
                "name": "United States",
                "sort-name": "United States",
                "iso-3166-1-codes": [
                  "US"
                ]
              }
            }
          ],
          "track-count": 11,
          "media": [
            {
              "id": "460f0873-c4e4-3b4e-a8c7-faa2762a570c",
              "position": 1,
              "track": [
                {
                  "id": "77afb1d8-5324-33f4-833f-ccf0e5e7d273",
                  "number": "1",
                  "title": "Low Man's Lyric",
                  "length": 439760
                }
              ],
              "track-count": 11,
              "track-offset": 0
            }
          ]
        }
      ],
      "tags": [
        {
          "count": 1,
          "name": "heavy metal"
        },
        {
          "count": 1,
          "name": "thrash metal"
        },
        {
          "count": 2,
          "name": "metal"
        },
        {
          "count": 1,
          "name": "hard rock"
        }
      ]
    },
    {
      "id": "e38951e5-8796-4571-8f89-984f5a91f495",
      "score": 100,
      "artist-credit-id": "7403167d-416b-3dee-96c6-4725d8c3eed3",
      "title": "Low Man's Lyric",
      "length": 475000,
      "disambiguation": "live, 1998-05-08: Yoyogi Olympic Pool, Tokyo, Japan",
      "video": null,
      "artist-credit": [
        {
          "name": "Metallica",
          "artist": {
            "id": "65f4f0c5-ef9e-490c-aee3-909e7ae6b2ab",
            "name": "Metallica",
            "sort-name": "Metallica",
            "aliases": [
              {
                "sort-name": "\u30e1\u30bf\u30ea\u30ab",
                "type-id": "894afba6-2816-3c24-8072-eadb66bd04bc",
                "name": "\u30e1\u30bf\u30ea\u30ab",
                "locale": "ja",
                "type": "Artist name",
                "primary": true,
                "begin-date": null,
                "end-date": null
              },
              {
                "sort-name": "Metalica",
                "type-id": "1937e404-b981-3cb7-8151-4c86ebfc8d8e",
                "name": "Metalica",
                "locale": null,
                "type": "Search hint",
                "primary": null,
                "begin-date": null,
                "end-date": null
              },
              {
                "sort-name": "\uba54\ud0c8\ub9ac\uce74",
                "name": "\uba54\ud0c8\ub9ac\uce74",
                "locale": "ko_KR",
                "type": null,
                "primary": true,
                "begin-date": null,
                "end-date": null
              },
              {
                "sort-name": "Metallica",
                "type-id": "894afba6-2816-3c24-8072-eadb66bd04bc",
                "name": "Metallica",
                "locale": "en",
                "type": "Artist name",
                "primary": true,
                "begin-date": null,
                "end-date": null
              }
            ]
          }
        }
      ],
      "releases": [
        {
          "id": "889e65ad-eb8f-4cdd-9ca6-3c98495f0eea",
          "status-id": "4e304316-386d-3409-af2e-78857eec5cfe",
          "artist-credit-id": "7403167d-416b-3dee-96c6-4725d8c3eed3",
          "count": 1,
          "title": "1998-05-08: Yoyogi Olympic Pool, Tokyo, Japan",
          "status": "Official",
          "artist-credit": [
            {
              "name": "Metallica",
              "artist": {
                "id": "65f4f0c5-ef9e-490c-aee3-909e7ae6b2ab",
                "name": "Metallica",
                "sort-name": "Metallica"
              }
            }
          ],
          "release-group": {
            "id": "fd771603-38f8-44f7-aa76-d0d42bb1156e",
            "type-id": "6fd474e2-6b58-3102-9d17-d6f7eb7da0a0",
            "primary-type-id": "f529b476-6e62-324f-b0aa-1f3e33d313fc",
            "title": "1998-05-08: Yoyogi Olympic Pool, Tokyo, Japan",
            "primary-type": "Album",
            "secondary-types": [
              "Live"
            ],
            "secondary-type-ids": [
              "6fd474e2-6b58-3102-9d17-d6f7eb7da0a0"
            ]
          },
          "track-count": 21,
          "media": [
            {
              "id": "2a8f2c85-cf2c-3f5c-b948-e7d39ed7e4e1",
              "position": 1,
              "format": "Digital Media",
              "track": [
                {
                  "id": "7010f31f-ae95-4d60-a530-394843f15e46",
                  "number": "16",
                  "title": "Low Man's Lyric",
                  "length": 475000
                }
              ],
              "track-count": 21,
              "track-offset": 15
            }
          ]
        }
      ]
    },
    {
      "id": "b0fe7471-4784-4b3d-b01a-5c669069a7d1",
      "score": 100,
      "artist-credit-id": "7403167d-416b-3dee-96c6-4725d8c3eed3",
      "title": "Low Man's Lyric",
      "length": 437000,
      "disambiguation": "live, 1997-12-18: Acoustica: KSJO Studio, San Jose, CA, USA",
      "video": null,
      "artist-credit": [
        {
          "name": "Metallica",
          "artist": {
            "id": "65f4f0c5-ef9e-490c-aee3-909e7ae6b2ab",
            "name": "Metallica",
            "sort-name": "Metallica",
            "aliases": [
              {
                "sort-name": "\u30e1\u30bf\u30ea\u30ab",
                "type-id": "894afba6-2816-3c24-8072-eadb66bd04bc",
                "name": "\u30e1\u30bf\u30ea\u30ab",
                "locale": "ja",
                "type": "Artist name",
                "primary": true,
                "begin-date": null,
                "end-date": null
              },
              {
                "sort-name": "Metalica",
                "type-id": "1937e404-b981-3cb7-8151-4c86ebfc8d8e",
                "name": "Metalica",
                "locale": null,
                "type": "Search hint",
                "primary": null,
                "begin-date": null,
                "end-date": null
              },
              {
                "sort-name": "\uba54\ud0c8\ub9ac\uce74",
                "name": "\uba54\ud0c8\ub9ac\uce74",
                "locale": "ko_KR",
                "type": null,
                "primary": true,
                "begin-date": null,
                "end-date": null
              },
              {
                "sort-name": "Metallica",
                "type-id": "894afba6-2816-3c24-8072-eadb66bd04bc",
                "name": "Metallica",
                "locale": "en",
                "type": "Artist name",
                "primary": true,
                "begin-date": null,
                "end-date": null
              }
            ]
          }
        }
      ],
      "first-release-date": "1999",
      "releases": [
        {
          "id": "ae5e870b-e9bc-4377-9556-3aa649a840c7",
          "status-id": "1156806e-d06a-38bd-83f0-cf2284a808b9",
          "artist-credit-id": "7403167d-416b-3dee-96c6-4725d8c3eed3",
          "count": 1,
          "title": "The Golden Unplugged Album",
          "status": "Bootleg",
          "artist-credit": [
            {
              "name": "Metallica",
              "artist": {
                "id": "65f4f0c5-ef9e-490c-aee3-909e7ae6b2ab",
                "name": "Metallica",
                "sort-name": "Metallica"
              }
            }
          ],
          "release-group": {
            "id": "065a6793-3676-3f76-ada7-476efde321f2",
            "type-id": "dd2a21e1-0c00-3729-a7a0-de60b84eb5d1",
            "primary-type-id": "f529b476-6e62-324f-b0aa-1f3e33d313fc",
            "title": "The Golden Unplugged Album",
            "primary-type": "Album",
            "secondary-types": [
              "Compilation"
            ],
            "secondary-type-ids": [
              "dd2a21e1-0c00-3729-a7a0-de60b84eb5d1"
            ]
          },
          "date": "1999",
          "country": "XE",
          "release-events": [
            {
              "date": "1999",
              "area": {
                "id": "89a675c2-3e37-3518-b83c-418bad59a85a",
                "name": "Europe",
                "sort-name": "Europe",
                "iso-3166-1-codes": [
                  "XE"
                ]
              }
            }
          ],
          "track-count": 13,
          "media": [
            {
              "id": "c2c35280-3912-3a61-b53c-8bcdee14a5c8",
              "position": 1,
              "format": "CD",
              "track": [
                {
                  "id": "64cb4675-de65-4a24-9b53-9592af475114",
                  "number": "2",
                  "title": "Low Man's Lyric (live, KSJO FM Studios, December 18th, 1997)",
                  "length": 437000
                }
              ],
              "track-count": 13,
              "track-offset": 1
            }
          ]
        }
      ]
    },
    {
      "id": "50ef0eef-3693-42b0-b5ff-9175650f676f",
      "score": 100,
      "artist-credit-id": "7403167d-416b-3dee-96c6-4725d8c3eed3",
      "title": "Low Man\u2019s Lyric",
      "length": 457400,
      "video": null,
      "artist-credit": [
        {
          "name": "Metallica",
          "artist": {
            "id": "65f4f0c5-ef9e-490c-aee3-909e7ae6b2ab",
            "name": "Metallica",
            "sort-name": "Metallica",
            "aliases": [
              {
                "sort-name": "\u30e1\u30bf\u30ea\u30ab",
                "type-id": "894afba6-2816-3c24-8072-eadb66bd04bc",
                "name": "\u30e1\u30bf\u30ea\u30ab",
                "locale": "ja",
                "type": "Artist name",
                "primary": true,
                "begin-date": null,
                "end-date": null
              },
              {
                "sort-name": "Metalica",
                "type-id": "1937e404-b981-3cb7-8151-4c86ebfc8d8e",
                "name": "Metalica",
                "locale": null,
                "type": "Search hint",
                "primary": null,
                "begin-date": null,
                "end-date": null
              },
              {
                "sort-name": "\uba54\ud0c8\ub9ac\uce74",
                "name": "\uba54\ud0c8\ub9ac\uce74",
                "locale": "ko_KR",
                "type": null,
                "primary": true,
                "begin-date": null,
                "end-date": null
              },
              {
                "sort-name": "Metallica",
                "type-id": "894afba6-2816-3c24-8072-eadb66bd04bc",
                "name": "Metallica",
                "locale": "en",
                "type": "Artist name",
                "primary": true,
                "begin-date": null,
                "end-date": null
              }
            ]
          }
        }
      ],
      "first-release-date": "1997-11-15",
      "releases": [
        {
          "id": "f5e0f42d-872f-494c-aba5-59a052e543b8",
          "status-id": "4e304316-386d-3409-af2e-78857eec5cfe",
          "artist-credit-id": "7403167d-416b-3dee-96c6-4725d8c3eed3",
          "count": 2,
          "title": "Reload",
          "status": "Official",
          "artist-credit": [
            {
              "name": "Metallica",
              "artist": {
                "id": "65f4f0c5-ef9e-490c-aee3-909e7ae6b2ab",
                "name": "Metallica",
                "sort-name": "Metallica"
              }
            }
          ],
          "release-group": {
            "id": "8fd32554-02a7-3788-a761-7012e0e75e55",
            "type-id": "f529b476-6e62-324f-b0aa-1f3e33d313fc",
            "primary-type-id": "f529b476-6e62-324f-b0aa-1f3e33d313fc",
            "title": "Reload",
            "primary-type": "Album"
          },
          "date": "2014-08-25",
          "country": "US",
          "release-events": [
            {
              "date": "2014-08-25",
              "area": {
                "id": "489ce91b-6658-3307-9877-795b68554c98",
                "name": "United States",
                "sort-name": "United States",
                "iso-3166-1-codes": [
                  "US"
                ]
              }
            }
          ],
          "track-count": 13,
          "media": [
            {
              "id": "3a96b41e-d54f-4edd-b2dd-12994bdac314",
              "position": 2,
              "format": "12\" Vinyl",
              "track": [
                {
                  "id": "9ef830d5-fcc5-4fe4-855d-996abd270f29",
                  "number": "D1",
                  "title": "Low Man\u2019s Lyric"
                }
              ],
              "track-count": 6,
              "track-offset": 3
            }
          ]
        },
        {
          "id": "f3bb741a-b7e2-46dd-b9cc-b3289f9c49e9",
          "status-id": "4e304316-386d-3409-af2e-78857eec5cfe",
          "artist-credit-id": "7403167d-416b-3dee-96c6-4725d8c3eed3",
          "count": 2,
          "title": "Reload",
          "status": "Official",
          "artist-credit": [
            {
              "name": "Metallica",
              "artist": {
                "id": "65f4f0c5-ef9e-490c-aee3-909e7ae6b2ab",
                "name": "Metallica",
                "sort-name": "Metallica"
              }
            }
          ],
          "release-group": {
            "id": "8fd32554-02a7-3788-a761-7012e0e75e55",
            "type-id": "f529b476-6e62-324f-b0aa-1f3e33d313fc",
            "primary-type-id": "f529b476-6e62-324f-b0aa-1f3e33d313fc",
            "title": "Reload",
            "primary-type": "Album"
          },
          "date": "2015-07-24",
          "country": "XE",
          "release-events": [
            {
              "date": "2015-07-24",
              "area": {
                "id": "89a675c2-3e37-3518-b83c-418bad59a85a",
                "name": "Europe",
                "sort-name": "Europe",
                "iso-3166-1-codes": [
                  "XE"
                ]
              }
            }
          ],
          "track-count": 13,
          "media": [
            {
              "id": "73ef1f9b-c4de-44ac-8ba9-a6e19932ff95",
              "position": 2,
              "format": "12\" Vinyl",
              "track": [
                {
                  "id": "9a9ffe15-51f0-446a-9a2e-7b920776bcb6",
                  "number": "D1",
                  "title": "Low Man\u2019s Lyric"
                }
              ],
              "track-count": 6,
              "track-offset": 3
            }
          ]
        },
        {
          "id": "2fdbdd5d-fd22-4cdf-b689-e56bb8f76228",
          "status-id": "1156806e-d06a-38bd-83f0-cf2284a808b9",
          "artist-credit-id": "7403167d-416b-3dee-96c6-4725d8c3eed3",
          "count": 2,
          "title": "Best Ballads",
          "status": "Bootleg",
          "artist-credit": [
            {
              "name": "Metallica",
              "artist": {
                "id": "65f4f0c5-ef9e-490c-aee3-909e7ae6b2ab",
                "name": "Metallica",
                "sort-name": "Metallica"
              }
            }
          ],
          "release-group": {
            "id": "d4b6ff9a-0e99-386c-84c5-ec41e4514a93",
            "type-id": "dd2a21e1-0c00-3729-a7a0-de60b84eb5d1",
            "primary-type-id": "f529b476-6e62-324f-b0aa-1f3e33d313fc",
            "title": "Best Ballads",
            "primary-type": "Album",
            "secondary-types": [
              "Compilation"
            ],
            "secondary-type-ids": [
              "dd2a21e1-0c00-3729-a7a0-de60b84eb5d1"
            ]
          },
          "date": "",
          "country": "RU",
          "release-events": [
            {
              "date": "",
              "area": {
                "id": "1f1fc3a4-9500-39b8-9f10-f0a465557eef",
                "name": "Russia",
                "sort-name": "Russia",
                "iso-3166-1-codes": [
                  "RU"
                ]
              }
            }
          ],
          "track-count": 20,
          "media": [
            {
              "id": "a0a44901-810a-3c28-b94f-68f273af2590",
              "position": 1,
              "format": "CD",
              "track": [
                {
                  "id": "4b10ff08-ee8a-4458-9acb-3776f8cf5e5a",
                  "number": "6",
                  "title": "Low Man\u2019s Lyric",
                  "length": 459400
                }
              ],
              "track-count": 11,
              "track-offset": 5
            }
          ]
        },
        {
          "id": "2ed76b0e-49f9-41c2-b4ae-94fb768f09f4",
          "artist-credit-id": "7403167d-416b-3dee-96c6-4725d8c3eed3",
          "count": 2,
          "title": "The Best Ballads",
          "artist-credit": [
            {
              "name": "Metallica",
              "artist": {
                "id": "65f4f0c5-ef9e-490c-aee3-909e7ae6b2ab",
                "name": "Metallica",
                "sort-name": "Metallica"
              }
            }
          ],
          "release-group": {
            "id": "dedb420e-6586-4695-afcb-31566222ced9",
            "type-id": "dd2a21e1-0c00-3729-a7a0-de60b84eb5d1",
            "primary-type-id": "f529b476-6e62-324f-b0aa-1f3e33d313fc",
            "title": "The Best Ballads",
            "primary-type": "Album",
            "secondary-types": [
              "Compilation"
            ],
            "secondary-type-ids": [
              "dd2a21e1-0c00-3729-a7a0-de60b84eb5d1"
            ]
          },
          "date": "2005",
          "country": "UA",
          "release-events": [
            {
              "date": "2005",
              "area": {
                "id": "904768d0-61ca-3c40-93ac-93adc36fef4b",
                "name": "Ukraine",
                "sort-name": "Ukraine",
                "iso-3166-1-codes": [
                  "UA"
                ]
              }
            }
          ],
          "track-count": 20,
          "media": [
            {
              "id": "9a87f963-ff0a-4a0a-89bf-1fc3482482b3",
              "position": 1,
              "format": "CD",
              "track": [
                {
                  "id": "1fe97ce0-9c43-4cd1-b37d-d1ae95ca470a",
                  "number": "6",
                  "title": "Low Man\u2019s Lyric",
                  "length": 459400
                }
              ],
              "track-count": 11,
              "track-offset": 5
            }
          ]
        },
        {
          "id": "607074e7-7ff6-496b-a088-69b372975108",
          "status-id": "4e304316-386d-3409-af2e-78857eec5cfe",
          "artist-credit-id": "7403167d-416b-3dee-96c6-4725d8c3eed3",
          "count": 1,
          "title": "Reload",
          "status": "Official",
          "artist-credit": [
            {
              "name": "Metallica",
              "artist": {
                "id": "65f4f0c5-ef9e-490c-aee3-909e7ae6b2ab",
                "name": "Metallica",
                "sort-name": "Metallica"
              }
            }
          ],
          "release-group": {
            "id": "8fd32554-02a7-3788-a761-7012e0e75e55",
            "type-id": "f529b476-6e62-324f-b0aa-1f3e33d313fc",
            "primary-type-id": "f529b476-6e62-324f-b0aa-1f3e33d313fc",
            "title": "Reload",
            "primary-type": "Album"
          },
          "date": "2020-03-27",
          "country": "CA",
          "release-events": [
            {
              "date": "2020-03-27",
              "area": {
                "id": "71bbafaa-e825-3e15-8ca9-017dcad1748b",
                "name": "Canada",
                "sort-name": "Canada",
                "iso-3166-1-codes": [
                  "CA"
                ]
              }
            },
            {
              "date": "2020-03-27",
              "area": {
                "id": "489ce91b-6658-3307-9877-795b68554c98",
                "name": "United States",
                "sort-name": "United States",
                "iso-3166-1-codes": [
                  "US"
                ]
              }
            }
          ],
          "track-count": 13,
          "media": [
            {
              "id": "8ef90b6d-948d-343b-aa12-b4ac140073cc",
              "position": 1,
              "format": "Digital Media",
              "track": [
                {
                  "id": "7c7c575d-c316-4806-9513-80a5b28b73f3",
                  "number": "11",
                  "title": "Low Man\u2019s Lyric",
                  "length": 457400
                }
              ],
              "track-count": 13,
              "track-offset": 10
            }
          ]
        },
        {
          "id": "da87cbd8-c2ed-411a-ba8c-1a335a10010a",
          "status-id": "4e304316-386d-3409-af2e-78857eec5cfe",
          "artist-credit-id": "7403167d-416b-3dee-96c6-4725d8c3eed3",
          "count": 16,
          "title": "The Metallica Collection",
          "status": "Official",
          "artist-credit": [
            {
              "name": "Metallica",
              "artist": {
                "id": "65f4f0c5-ef9e-490c-aee3-909e7ae6b2ab",
                "name": "Metallica",
                "sort-name": "Metallica"
              }
            }
          ],
          "release-group": {
            "id": "5b2a6048-030a-4e04-b2f5-eaf02000725f",
            "type-id": "dd2a21e1-0c00-3729-a7a0-de60b84eb5d1",
            "primary-type-id": "f529b476-6e62-324f-b0aa-1f3e33d313fc",
            "title": "The Metallica Collection",
            "primary-type": "Album",
            "secondary-types": [
              "Compilation"
            ],
            "secondary-type-ids": [
              "dd2a21e1-0c00-3729-a7a0-de60b84eb5d1"
            ]
          },
          "date": "2009-04-25",
          "country": "XW",
          "release-events": [
            {
              "date": "2009-04-25",
              "area": {
                "id": "525d4e18-3d00-31b9-a58b-a146a916de8f",
                "name": "[Worldwide]",
                "sort-name": "[Worldwide]",
                "iso-3166-1-codes": [
                  "XW"
                ]
              }
            }
          ],
          "track-count": 163,
          "media": [
            {
              "id": "e91dd40a-fa48-314a-b179-9ccbb09277e4",
              "position": 7,
              "format": "Digital Media",
              "track": [
                {
                  "id": "e4ab0610-7ca6-4349-9018-80aeb8d8bdd7",
                  "number": "11",
                  "title": "Low Man\u2019s Lyric",
                  "length": 457000
                }
              ],
              "track-count": 13,
              "track-offset": 10
            }
          ]
        },
        {
          "id": "d701f448-5cba-4303-80c8-0bb63537fdb1",
          "status-id": "4e304316-386d-3409-af2e-78857eec5cfe",
          "artist-credit-id": "7403167d-416b-3dee-96c6-4725d8c3eed3",
          "count": 1,
          "title": "Reload",
          "status": "Official",
          "artist-credit": [
            {
              "name": "Metallica",
              "artist": {
                "id": "65f4f0c5-ef9e-490c-aee3-909e7ae6b2ab",
                "name": "Metallica",
                "sort-name": "Metallica"
              }
            }
          ],
          "release-group": {
            "id": "8fd32554-02a7-3788-a761-7012e0e75e55",
            "type-id": "f529b476-6e62-324f-b0aa-1f3e33d313fc",
            "primary-type-id": "f529b476-6e62-324f-b0aa-1f3e33d313fc",
            "title": "Reload",
            "primary-type": "Album"
          },
          "date": "1997",
          "country": "US",
          "release-events": [
            {
              "date": "1997",
              "area": {
                "id": "489ce91b-6658-3307-9877-795b68554c98",
                "name": "United States",
                "sort-name": "United States",
                "iso-3166-1-codes": [
                  "US"
                ]
              }
            }
          ],
          "track-count": 13,
          "media": [
            {
              "id": "2ef7c48f-c7cc-353b-8293-0f5c9be553b3",
              "position": 1,
              "format": "Cassette",
              "track": [
                {
                  "id": "d435e776-1d63-45f1-b702-65d582b553c3",
                  "number": "11",
                  "title": "Low Man\u2019s Lyric",
                  "length": 457400
                }
              ],
              "track-count": 13,
              "track-offset": 10
            }
          ]
        },
        {
          "id": "a03b76c6-c2d5-4e8b-89a4-185fce6b321b",
          "status-id": "4e304316-386d-3409-af2e-78857eec5cfe",
          "artist-credit-id": "7403167d-416b-3dee-96c6-4725d8c3eed3",
          "count": 1,
          "title": "Reload",
          "status": "Official",
          "artist-credit": [
            {
              "name": "Metallica",
              "artist": {
                "id": "65f4f0c5-ef9e-490c-aee3-909e7ae6b2ab",
                "name": "Metallica",
                "sort-name": "Metallica"
              }
            }
          ],
          "release-group": {
            "id": "8fd32554-02a7-3788-a761-7012e0e75e55",
            "type-id": "f529b476-6e62-324f-b0aa-1f3e33d313fc",
            "primary-type-id": "f529b476-6e62-324f-b0aa-1f3e33d313fc",
            "title": "Reload",
            "primary-type": "Album"
          },
          "date": "1997",
          "country": "MX",
          "release-events": [
            {
              "date": "1997",
              "area": {
                "id": "3e08b2cd-69f3-317c-b1e4-e71be581839e",
                "name": "Mexico",
                "sort-name": "Mexico",
                "iso-3166-1-codes": [
                  "MX"
                ]
              }
            }
          ],
          "track-count": 13,
          "media": [
            {
              "id": "ee0d9b89-dab2-35f1-b8fd-54d996101456",
              "position": 1,
              "format": "CD",
              "track": [
                {
                  "id": "62232d84-99c7-4d8c-957f-2d56b88891d2",
                  "number": "11",
                  "title": "Low Man\u2019s Lyric",
                  "length": 457400
                }
              ],
              "track-count": 13,
              "track-offset": 10
            }
          ]
        },
        {
          "id": "e554e2a4-f5f7-4a55-9da5-7bf252319633",
          "status-id": "518ffc83-5cde-34df-8627-81bff5093d92",
          "artist-credit-id": "7403167d-416b-3dee-96c6-4725d8c3eed3",
          "count": 1,
          "title": "Reload",
          "status": "Promotion",
          "artist-credit": [
            {
              "name": "Metallica",
              "artist": {
                "id": "65f4f0c5-ef9e-490c-aee3-909e7ae6b2ab",
                "name": "Metallica",
                "sort-name": "Metallica"
              }
            }
          ],
          "release-group": {
            "id": "8fd32554-02a7-3788-a761-7012e0e75e55",
            "type-id": "f529b476-6e62-324f-b0aa-1f3e33d313fc",
            "primary-type-id": "f529b476-6e62-324f-b0aa-1f3e33d313fc",
            "title": "Reload",
            "primary-type": "Album"
          },
          "date": "1997",
          "country": "US",
          "release-events": [
            {
              "date": "1997",
              "area": {
                "id": "489ce91b-6658-3307-9877-795b68554c98",
                "name": "United States",
                "sort-name": "United States",
                "iso-3166-1-codes": [
                  "US"
                ]
              }
            }
          ],
          "track-count": 13,
          "media": [
            {
              "id": "5b39c2f5-330d-30f2-898e-052a7b2ee280",
              "position": 1,
              "format": "CD",
              "track": [
                {
                  "id": "56e52633-8737-4f03-9422-ccd604a96026",
                  "number": "11",
                  "title": "Low Man\u2019s Lyric",
                  "length": 457266
                }
              ],
              "track-count": 13,
              "track-offset": 10
            }
          ]
        },
        {
          "id": "ee9aafd9-2f73-4cf7-acf4-3523c5a61ca2",
          "status-id": "4e304316-386d-3409-af2e-78857eec5cfe",
          "artist-credit-id": "7403167d-416b-3dee-96c6-4725d8c3eed3",
          "count": 1,
          "title": "Reload",
          "status": "Official",
          "artist-credit": [
            {
              "name": "Metallica",
              "artist": {
                "id": "65f4f0c5-ef9e-490c-aee3-909e7ae6b2ab",
                "name": "Metallica",
                "sort-name": "Metallica"
              }
            }
          ],
          "release-group": {
            "id": "8fd32554-02a7-3788-a761-7012e0e75e55",
            "type-id": "f529b476-6e62-324f-b0aa-1f3e33d313fc",
            "primary-type-id": "f529b476-6e62-324f-b0aa-1f3e33d313fc",
            "title": "Reload",
            "primary-type": "Album"
          },
          "date": "2005-10-01",
          "country": "AU",
          "release-events": [
            {
              "date": "2005-10-01",
              "area": {
                "id": "106e0bec-b638-3b37-b731-f53d507dc00e",
                "name": "Australia",
                "sort-name": "Australia",
                "iso-3166-1-codes": [
                  "AU"
                ]
              }
            }
          ],
          "track-count": 13,
          "media": [
            {
              "id": "07f3ba70-0aec-3168-a5ca-9ffcd17c34e4",
              "position": 1,
              "format": "CD",
              "track": [
                {
                  "id": "b10b699b-e57e-43aa-a037-01d231866f8c",
                  "number": "11",
                  "title": "Low Man\u2019s Lyric",
                  "length": 457400
                }
              ],
              "track-count": 13,
              "track-offset": 10
            }
          ]
        },
        {
          "id": "64c581c6-7270-3f3a-8dd2-3fb14a41d679",
          "status-id": "4e304316-386d-3409-af2e-78857eec5cfe",
          "artist-credit-id": "7403167d-416b-3dee-96c6-4725d8c3eed3",
          "count": 1,
          "title": "Reload",
          "status": "Official",
          "artist-credit": [
            {
              "name": "Metallica",
              "artist": {
                "id": "65f4f0c5-ef9e-490c-aee3-909e7ae6b2ab",
                "name": "Metallica",
                "sort-name": "Metallica"
              }
            }
          ],
          "release-group": {
            "id": "8fd32554-02a7-3788-a761-7012e0e75e55",
            "type-id": "f529b476-6e62-324f-b0aa-1f3e33d313fc",
            "primary-type-id": "f529b476-6e62-324f-b0aa-1f3e33d313fc",
            "title": "Reload",
            "primary-type": "Album"
          },
          "date": "1997-11-15",
          "country": "JP",
          "release-events": [
            {
              "date": "1997-11-15",
              "area": {
                "id": "2db42837-c832-3c27-b4a3-08198f75693c",
                "name": "Japan",
                "sort-name": "Japan",
                "iso-3166-1-codes": [
                  "JP"
                ]
              }
            }
          ],
          "track-count": 13,
          "media": [
            {
              "id": "e3f44f50-7346-3186-84d3-b5c6955e380e",
              "position": 1,
              "format": "CD",
              "track": [
                {
                  "id": "4284d5c5-9d51-3cbf-ab3b-7c8407bad624",
                  "number": "11",
                  "title": "Low Man\u2019s Lyric",
                  "length": 457400
                }
              ],
              "track-count": 13,
              "track-offset": 10
            }
          ]
        },
        {
          "id": "aef5108a-3dc0-3ba7-bfd7-dc95a3b186fe",
          "status-id": "4e304316-386d-3409-af2e-78857eec5cfe",
          "artist-credit-id": "7403167d-416b-3dee-96c6-4725d8c3eed3",
          "count": 1,
          "title": "Reload",
          "status": "Official",
          "artist-credit": [
            {
              "name": "Metallica",
              "artist": {
                "id": "65f4f0c5-ef9e-490c-aee3-909e7ae6b2ab",
                "name": "Metallica",
                "sort-name": "Metallica"
              }
            }
          ],
          "release-group": {
            "id": "8fd32554-02a7-3788-a761-7012e0e75e55",
            "type-id": "f529b476-6e62-324f-b0aa-1f3e33d313fc",
            "primary-type-id": "f529b476-6e62-324f-b0aa-1f3e33d313fc",
            "title": "Reload",
            "primary-type": "Album"
          },
          "date": "2003-11-06",
          "country": "JP",
          "release-events": [
            {
              "date": "2003-11-06",
              "area": {
                "id": "2db42837-c832-3c27-b4a3-08198f75693c",
                "name": "Japan",
                "sort-name": "Japan",
                "iso-3166-1-codes": [
                  "JP"
                ]
              }
            }
          ],
          "track-count": 13,
          "media": [
            {
              "id": "2a9e7b43-7add-3ad5-8e81-b98cb8a70f49",
              "position": 1,
              "format": "CD",
              "track": [
                {
                  "id": "9b463dab-79b8-3ec5-8842-14e552f7bee9",
                  "number": "11",
                  "title": "Low Man\u2019s Lyric",
                  "length": 457400
                }
              ],
              "track-count": 13,
              "track-offset": 10
            }
          ]
        },
        {
          "id": "bddf6165-f5c9-4b0e-9990-98a3f8dfd831",
          "status-id": "4e304316-386d-3409-af2e-78857eec5cfe",
          "artist-credit-id": "7403167d-416b-3dee-96c6-4725d8c3eed3",
          "count": 1,
          "title": "Reload",
          "status": "Official",
          "artist-credit": [
            {
              "name": "Metallica",
              "artist": {
                "id": "65f4f0c5-ef9e-490c-aee3-909e7ae6b2ab",
                "name": "Metallica",
                "sort-name": "Metallica"
              }
            }
          ],
          "release-group": {
            "id": "8fd32554-02a7-3788-a761-7012e0e75e55",
            "type-id": "f529b476-6e62-324f-b0aa-1f3e33d313fc",
            "primary-type-id": "f529b476-6e62-324f-b0aa-1f3e33d313fc",
            "title": "Reload",
            "primary-type": "Album"
          },
          "date": "1997-11",
          "country": "CA",
          "release-events": [
            {
              "date": "1997-11",
              "area": {
                "id": "71bbafaa-e825-3e15-8ca9-017dcad1748b",
                "name": "Canada",
                "sort-name": "Canada",
                "iso-3166-1-codes": [
                  "CA"
                ]
              }
            }
          ],
          "track-count": 13,
          "media": [
            {
              "id": "33d14b99-a76a-3c10-882b-c3bb4f9599ce",
              "position": 1,
              "format": "CD",
              "track": [
                {
                  "id": "8d11287c-45f7-4d0c-b650-4714493f9f2c",
                  "number": "11",
                  "title": "Low Man\u2019s Lyric",
                  "length": 457400
                }
              ],
              "track-count": 13,
              "track-offset": 10
            }
          ]
        },
        {
          "id": "7d5fe166-a163-4887-8a53-ab6faa3154ab",
          "status-id": "4e304316-386d-3409-af2e-78857eec5cfe",
          "artist-credit-id": "7403167d-416b-3dee-96c6-4725d8c3eed3",
          "count": 1,
          "title": "Reload",
          "status": "Official",
          "artist-credit": [
            {
              "name": "Metallica",
              "artist": {
                "id": "65f4f0c5-ef9e-490c-aee3-909e7ae6b2ab",
                "name": "Metallica",
                "sort-name": "Metallica"
              }
            }
          ],
          "release-group": {
            "id": "8fd32554-02a7-3788-a761-7012e0e75e55",
            "type-id": "f529b476-6e62-324f-b0aa-1f3e33d313fc",
            "primary-type-id": "f529b476-6e62-324f-b0aa-1f3e33d313fc",
            "title": "Reload",
            "primary-type": "Album"
          },
          "date": "2008-09-12",
          "country": "JP",
          "release-events": [
            {
              "date": "2008-09-12",
              "area": {
                "id": "2db42837-c832-3c27-b4a3-08198f75693c",
                "name": "Japan",
                "sort-name": "Japan",
                "iso-3166-1-codes": [
                  "JP"
                ]
              }
            }
          ],
          "track-count": 13,
          "media": [
            {
              "id": "0b6ae57f-3f1f-39f5-9d8b-be75829bd526",
              "position": 1,
              "format": "SHM-CD",
              "track": [
                {
                  "id": "9668eb6a-7d8c-4002-9652-b6958d6f45ac",
                  "number": "11",
                  "title": "Low Man\u2019s Lyric",
                  "length": 457400
                }
              ],
              "track-count": 13,
              "track-offset": 10
            }
          ]
        },
        {
          "id": "430cbc8b-ccb6-4679-a147-85b297d8afb4",
          "status-id": "4e304316-386d-3409-af2e-78857eec5cfe",
          "artist-credit-id": "7403167d-416b-3dee-96c6-4725d8c3eed3",
          "count": 1,
          "title": "Reload",
          "status": "Official",
          "artist-credit": [
            {
              "name": "Metallica",
              "artist": {
                "id": "65f4f0c5-ef9e-490c-aee3-909e7ae6b2ab",
                "name": "Metallica",
                "sort-name": "Metallica"
              }
            }
          ],
          "release-group": {
            "id": "8fd32554-02a7-3788-a761-7012e0e75e55",
            "type-id": "f529b476-6e62-324f-b0aa-1f3e33d313fc",
            "primary-type-id": "f529b476-6e62-324f-b0aa-1f3e33d313fc",
            "title": "Reload",
            "primary-type": "Album"
          },
          "date": "2010-09-22",
          "country": "JP",
          "release-events": [
            {
              "date": "2010-09-22",
              "area": {
                "id": "2db42837-c832-3c27-b4a3-08198f75693c",
                "name": "Japan",
                "sort-name": "Japan",
                "iso-3166-1-codes": [
                  "JP"
                ]
              }
            }
          ],
          "track-count": 13,
          "media": [
            {
              "id": "fc31634d-a105-326b-8a58-d08e4e555de2",
              "position": 1,
              "format": "SHM-CD",
              "track": [
                {
                  "id": "927993e6-5887-36df-90cc-54638b98e8c4",
                  "number": "11",
                  "title": "Low Man\u2019s Lyric",
                  "length": 457400
                }
              ],
              "track-count": 13,
              "track-offset": 10
            }
          ]
        },
        {
          "id": "6294a007-9c2c-44cc-92bb-36dba3540b28",
          "status-id": "4e304316-386d-3409-af2e-78857eec5cfe",
          "artist-credit-id": "7403167d-416b-3dee-96c6-4725d8c3eed3",
          "count": 1,
          "title": "Reload",
          "status": "Official",
          "artist-credit": [
            {
              "name": "Metallica",
              "artist": {
                "id": "65f4f0c5-ef9e-490c-aee3-909e7ae6b2ab",
                "name": "Metallica",
                "sort-name": "Metallica"
              }
            }
          ],
          "release-group": {
            "id": "8fd32554-02a7-3788-a761-7012e0e75e55",
            "type-id": "f529b476-6e62-324f-b0aa-1f3e33d313fc",
            "primary-type-id": "f529b476-6e62-324f-b0aa-1f3e33d313fc",
            "title": "Reload",
            "primary-type": "Album"
          },
          "date": "1997",
          "country": "UA",
          "release-events": [
            {
              "date": "1997",
              "area": {
                "id": "904768d0-61ca-3c40-93ac-93adc36fef4b",
                "name": "Ukraine",
                "sort-name": "Ukraine",
                "iso-3166-1-codes": [
                  "UA"
                ]
              }
            }
          ],
          "track-count": 13,
          "media": [
            {
              "id": "9de7ea93-dbed-399b-b1cc-37547c317fdc",
              "position": 1,
              "format": "CD",
              "track": [
                {
                  "id": "775a972a-aefe-4ac4-9434-514d2475de20",
                  "number": "11",
                  "title": "Low Man\u2019s Lyric",
                  "length": 457400
                }
              ],
              "track-count": 13,
              "track-offset": 10
            }
          ]
        },
        {
          "id": "24a80f7b-5a67-4234-9760-e432768db279",
          "status-id": "4e304316-386d-3409-af2e-78857eec5cfe",
          "artist-credit-id": "7403167d-416b-3dee-96c6-4725d8c3eed3",
          "count": 1,
          "title": "Reload",
          "status": "Official",
          "artist-credit": [
            {
              "name": "Metallica",
              "artist": {
                "id": "65f4f0c5-ef9e-490c-aee3-909e7ae6b2ab",
                "name": "Metallica",
                "sort-name": "Metallica"
              }
            }
          ],
          "release-group": {
            "id": "8fd32554-02a7-3788-a761-7012e0e75e55",
            "type-id": "f529b476-6e62-324f-b0aa-1f3e33d313fc",
            "primary-type-id": "f529b476-6e62-324f-b0aa-1f3e33d313fc",
            "title": "Reload",
            "primary-type": "Album"
          },
          "date": "2006-08-09",
          "country": "JP",
          "release-events": [
            {
              "date": "2006-08-09",
              "area": {
                "id": "2db42837-c832-3c27-b4a3-08198f75693c",
                "name": "Japan",
                "sort-name": "Japan",
                "iso-3166-1-codes": [
                  "JP"
                ]
              }
            }
          ],
          "track-count": 13,
          "media": [
            {
              "id": "87490f17-01ea-3c91-bf7b-20dbae202954",
              "position": 1,
              "format": "CD",
              "track": [
                {
                  "id": "7f9043d8-204a-423a-ae93-aed97feed3bd",
                  "number": "11",
                  "title": "Low Man\u2019s Lyric",
                  "length": 457400
                }
              ],
              "track-count": 13,
              "track-offset": 10
            }
          ]
        },
        {
          "id": "ffb2e6a9-a32e-44ec-9e5f-67f5232d6fa5",
          "status-id": "4e304316-386d-3409-af2e-78857eec5cfe",
          "artist-credit-id": "7403167d-416b-3dee-96c6-4725d8c3eed3",
          "count": 1,
          "title": "Reload",
          "status": "Official",
          "artist-credit": [
            {
              "name": "Metallica",
              "artist": {
                "id": "65f4f0c5-ef9e-490c-aee3-909e7ae6b2ab",
                "name": "Metallica",
                "sort-name": "Metallica"
              }
            }
          ],
          "release-group": {
            "id": "8fd32554-02a7-3788-a761-7012e0e75e55",
            "type-id": "f529b476-6e62-324f-b0aa-1f3e33d313fc",
            "primary-type-id": "f529b476-6e62-324f-b0aa-1f3e33d313fc",
            "title": "Reload",
            "primary-type": "Album"
          },
          "date": "2013-09-23",
          "country": "US",
          "release-events": [
            {
              "date": "2013-09-23",
              "area": {
                "id": "489ce91b-6658-3307-9877-795b68554c98",
                "name": "United States",
                "sort-name": "United States",
                "iso-3166-1-codes": [
                  "US"
                ]
              }
            }
          ],
          "track-count": 13,
          "media": [
            {
              "id": "2a309509-8983-3a1d-92d8-094ace2ff438",
              "position": 1,
              "format": "CD",
              "track": [
                {
                  "id": "2f66e496-a3b6-4561-92b4-103f349c86e1",
                  "number": "11",
                  "title": "Low Man\u2019s Lyric",
                  "length": 457266
                }
              ],
              "track-count": 13,
              "track-offset": 10
            }
          ]
        },
        {
          "id": "c5efce77-b87d-4866-bbd5-c968f3c1e2fd",
          "status-id": "4e304316-386d-3409-af2e-78857eec5cfe",
          "artist-credit-id": "7403167d-416b-3dee-96c6-4725d8c3eed3",
          "count": 1,
          "title": "Reload",
          "status": "Official",
          "artist-credit": [
            {
              "name": "Metallica",
              "artist": {
                "id": "65f4f0c5-ef9e-490c-aee3-909e7ae6b2ab",
                "name": "Metallica",
                "sort-name": "Metallica"
              }
            }
          ],
          "release-group": {
            "id": "8fd32554-02a7-3788-a761-7012e0e75e55",
            "type-id": "f529b476-6e62-324f-b0aa-1f3e33d313fc",
            "primary-type-id": "f529b476-6e62-324f-b0aa-1f3e33d313fc",
            "title": "Reload",
            "primary-type": "Album"
          },
          "date": "1997-11-18",
          "country": "ZA",
          "release-events": [
            {
              "date": "1997-11-18",
              "area": {
                "id": "50cc7852-862e-30ae-aa82-385fe7135b7f",
                "name": "South Africa",
                "sort-name": "South Africa",
                "iso-3166-1-codes": [
                  "ZA"
                ]
              }
            }
          ],
          "track-count": 13,
          "media": [
            {
              "id": "beb0ed62-8d3f-3df7-9fb8-a75f51d17b06",
              "position": 1,
              "format": "CD",
              "track": [
                {
                  "id": "5838707a-9000-4f9e-a964-40c5e3971e24",
                  "number": "11",
                  "title": "Low Man's Lyric",
                  "length": 457426
                }
              ],
              "track-count": 13,
              "track-offset": 10
            }
          ]
        },
        {
          "id": "bef2cf50-4797-4026-b543-6ab6187d1ce2",
          "status-id": "4e304316-386d-3409-af2e-78857eec5cfe",
          "artist-credit-id": "7403167d-416b-3dee-96c6-4725d8c3eed3",
          "count": 4,
          "title": "Reload",
          "status": "Official",
          "artist-credit": [
            {
              "name": "Metallica",
              "artist": {
                "id": "65f4f0c5-ef9e-490c-aee3-909e7ae6b2ab",
                "name": "Metallica",
                "sort-name": "Metallica"
              }
            }
          ],
          "release-group": {
            "id": "8fd32554-02a7-3788-a761-7012e0e75e55",
            "type-id": "f529b476-6e62-324f-b0aa-1f3e33d313fc",
            "primary-type-id": "f529b476-6e62-324f-b0aa-1f3e33d313fc",
            "title": "Reload",
            "primary-type": "Album"
          },
          "date": "2010",
          "country": "XE",
          "release-events": [
            {
              "date": "2010",
              "area": {
                "id": "89a675c2-3e37-3518-b83c-418bad59a85a",
                "name": "Europe",
                "sort-name": "Europe",
                "iso-3166-1-codes": [
                  "XE"
                ]
              }
            }
          ],
          "track-count": 13,
          "media": [
            {
              "id": "dcb8116e-02f7-3d8e-934d-ae2097c62e60",
              "position": 4,
              "format": "12\" Vinyl",
              "track": [
                {
                  "id": "94a622cc-df54-4dfe-911c-72331bc113dd",
                  "number": "G1",
                  "title": "Low Man's Lyric",
                  "length": 456000
                }
              ],
              "track-count": 3,
              "track-offset": 0
            }
          ]
        },
        {
          "id": "9d8572b1-efc1-4fdd-ae9d-0e30237ca68a",
          "status-id": "1156806e-d06a-38bd-83f0-cf2284a808b9",
          "artist-credit-id": "7403167d-416b-3dee-96c6-4725d8c3eed3",
          "count": 2,
          "title": "The Best of the Best",
          "status": "Bootleg",
          "artist-credit": [
            {
              "name": "Metallica",
              "artist": {
                "id": "65f4f0c5-ef9e-490c-aee3-909e7ae6b2ab",
                "name": "Metallica",
                "sort-name": "Metallica"
              }
            }
          ],
          "release-group": {
            "id": "96c314dc-9178-465c-b11c-81e04e56316d",
            "type-id": "dd2a21e1-0c00-3729-a7a0-de60b84eb5d1",
            "primary-type-id": "f529b476-6e62-324f-b0aa-1f3e33d313fc",
            "title": "The Best of the Best",
            "primary-type": "Album",
            "secondary-types": [
              "Compilation"
            ],
            "secondary-type-ids": [
              "dd2a21e1-0c00-3729-a7a0-de60b84eb5d1"
            ]
          },
          "track-count": 19,
          "media": [
            {
              "id": "e35521df-0a57-3fe2-987e-ff93b13efa29",
              "position": 2,
              "format": "CD",
              "track": [
                {
                  "id": "70f423c0-3a42-44b9-8471-4ceb95ba3620",
                  "number": "6",
                  "title": "Low Man\u2019s Lyric",
                  "length": 457000
                }
              ],
              "track-count": 9,
              "track-offset": 5
            }
          ]
        },
        {
          "id": "8d6ec88c-570b-45c8-ae1b-9b3cdc0e5c0e",
          "status-id": "4e304316-386d-3409-af2e-78857eec5cfe",
          "artist-credit-id": "7403167d-416b-3dee-96c6-4725d8c3eed3",
          "count": 1,
          "title": "Reload",
          "status": "Official",
          "artist-credit": [
            {
              "name": "Metallica",
              "artist": {
                "id": "65f4f0c5-ef9e-490c-aee3-909e7ae6b2ab",
                "name": "Metallica",
                "sort-name": "Metallica"
              }
            }
          ],
          "release-group": {
            "id": "8fd32554-02a7-3788-a761-7012e0e75e55",
            "type-id": "f529b476-6e62-324f-b0aa-1f3e33d313fc",
            "primary-type-id": "f529b476-6e62-324f-b0aa-1f3e33d313fc",
            "title": "Reload",
            "primary-type": "Album"
          },
          "date": "1997",
          "country": "FR",
          "release-events": [
            {
              "date": "1997",
              "area": {
                "id": "08310658-51eb-3801-80de-5a0739207115",
                "name": "France",
                "sort-name": "France",
                "iso-3166-1-codes": [
                  "FR"
                ]
              }
            }
          ],
          "track-count": 13,
          "media": [
            {
              "id": "55ba4b32-1eb5-38d1-b547-fb1fccf368c0",
              "position": 1,
              "format": "CD",
              "track": [
                {
                  "id": "14335167-0f51-43cc-bdf8-9e79285e73ee",
                  "number": "11",
                  "title": "Low Man\u2019s Lyric",
                  "length": 456000
                }
              ],
              "track-count": 13,
              "track-offset": 10
            }
          ]
        },
        {
          "id": "b8073dfc-1b9c-4a63-adac-695210510fde",
          "status-id": "4e304316-386d-3409-af2e-78857eec5cfe",
          "artist-credit-id": "7403167d-416b-3dee-96c6-4725d8c3eed3",
          "count": 1,
          "title": "Reload",
          "status": "Official",
          "artist-credit": [
            {
              "name": "Metallica",
              "artist": {
                "id": "65f4f0c5-ef9e-490c-aee3-909e7ae6b2ab",
                "name": "Metallica",
                "sort-name": "Metallica"
              }
            }
          ],
          "release-group": {
            "id": "8fd32554-02a7-3788-a761-7012e0e75e55",
            "type-id": "f529b476-6e62-324f-b0aa-1f3e33d313fc",
            "primary-type-id": "f529b476-6e62-324f-b0aa-1f3e33d313fc",
            "title": "Reload",
            "primary-type": "Album"
          },
          "track-count": 13,
          "media": [
            {
              "id": "25e69b8e-e255-36d0-bae9-9ef1512831f7",
              "position": 1,
              "format": "Digital Media",
              "track": [
                {
                  "id": "e015ebb6-6b16-421e-8fa0-72df2a82f08d",
                  "number": "11",
                  "title": "Low Man\u2019s Lyric",
                  "length": 456000
                }
              ],
              "track-count": 13,
              "track-offset": 10
            }
          ]
        },
        {
          "id": "dd0d1969-8804-429b-aff9-9ee4cdc3e278",
          "status-id": "4e304316-386d-3409-af2e-78857eec5cfe",
          "artist-credit-id": "7403167d-416b-3dee-96c6-4725d8c3eed3",
          "count": 1,
          "title": "Reload",
          "status": "Official",
          "artist-credit": [
            {
              "name": "Metallica",
              "artist": {
                "id": "65f4f0c5-ef9e-490c-aee3-909e7ae6b2ab",
                "name": "Metallica",
                "sort-name": "Metallica"
              }
            }
          ],
          "release-group": {
            "id": "8fd32554-02a7-3788-a761-7012e0e75e55",
            "type-id": "f529b476-6e62-324f-b0aa-1f3e33d313fc",
            "primary-type-id": "f529b476-6e62-324f-b0aa-1f3e33d313fc",
            "title": "Reload",
            "primary-type": "Album"
          },
          "track-count": 13,
          "media": [
            {
              "id": "804f7025-9f76-34dd-b902-fa3548f415f9",
              "position": 1,
              "format": "Digital Media",
              "track": [
                {
                  "id": "b0254e0f-e971-4a93-80fd-c1441be9b31b",
                  "number": "11",
                  "title": "Low Man\u2019s Lyric",
                  "length": 457400
                }
              ],
              "track-count": 13,
              "track-offset": 10
            }
          ]
        },
        {
          "id": "4c77bcd6-0bb3-4366-815a-cb5ee574eef1",
          "status-id": "4e304316-386d-3409-af2e-78857eec5cfe",
          "artist-credit-id": "7403167d-416b-3dee-96c6-4725d8c3eed3",
          "count": 1,
          "title": "Reload",
          "status": "Official",
          "artist-credit": [
            {
              "name": "Metallica",
              "artist": {
                "id": "65f4f0c5-ef9e-490c-aee3-909e7ae6b2ab",
                "name": "Metallica",
                "sort-name": "Metallica"
              }
            }
          ],
          "release-group": {
            "id": "8fd32554-02a7-3788-a761-7012e0e75e55",
            "type-id": "f529b476-6e62-324f-b0aa-1f3e33d313fc",
            "primary-type-id": "f529b476-6e62-324f-b0aa-1f3e33d313fc",
            "title": "Reload",
            "primary-type": "Album"
          },
          "date": "2013",
          "country": "CA",
          "release-events": [
            {
              "date": "2013",
              "area": {
                "id": "71bbafaa-e825-3e15-8ca9-017dcad1748b",
                "name": "Canada",
                "sort-name": "Canada",
                "iso-3166-1-codes": [
                  "CA"
                ]
              }
            },
            {
              "date": "2013",
              "area": {
                "id": "489ce91b-6658-3307-9877-795b68554c98",
                "name": "United States",
                "sort-name": "United States",
                "iso-3166-1-codes": [
                  "US"
                ]
              }
            }
          ],
          "track-count": 13,
          "media": [
            {
              "id": "bf7445b7-3575-3e55-99a8-d1c08ff27eca",
              "position": 1,
              "format": "Digital Media",
              "track": [
                {
                  "id": "74f7fe86-63f6-4d51-8fe4-5d366406ecb7",
                  "number": "11",
                  "title": "Low Man\u2019s Lyric",
                  "length": 457400
                }
              ],
              "track-count": 13,
              "track-offset": 10
            }
          ]
        },
        {
          "id": "fdf8ce06-f9b7-47be-8657-615819533de1",
          "status-id": "4e304316-386d-3409-af2e-78857eec5cfe",
          "artist-credit-id": "7403167d-416b-3dee-96c6-4725d8c3eed3",
          "count": 2,
          "title": "Reload",
          "status": "Official",
          "artist-credit": [
            {
              "name": "Metallica",
              "artist": {
                "id": "65f4f0c5-ef9e-490c-aee3-909e7ae6b2ab",
                "name": "Metallica",
                "sort-name": "Metallica"
              }
            }
          ],
          "release-group": {
            "id": "8fd32554-02a7-3788-a761-7012e0e75e55",
            "type-id": "f529b476-6e62-324f-b0aa-1f3e33d313fc",
            "primary-type-id": "f529b476-6e62-324f-b0aa-1f3e33d313fc",
            "title": "Reload",
            "primary-type": "Album"
          },
          "date": "2010",
          "country": "XE",
          "release-events": [
            {
              "date": "2010",
              "area": {
                "id": "89a675c2-3e37-3518-b83c-418bad59a85a",
                "name": "Europe",
                "sort-name": "Europe",
                "iso-3166-1-codes": [
                  "XE"
                ]
              }
            }
          ],
          "track-count": 13,
          "media": [
            {
              "id": "e47347a6-d3a7-3404-997e-7d72358a6952",
              "position": 2,
              "format": "12\" Vinyl",
              "track": [
                {
                  "id": "f8eb564c-5fdd-42ca-86ad-23608e4b205c",
                  "number": "D1",
                  "title": "Low Man\u2019s Lyric"
                }
              ],
              "track-count": 6,
              "track-offset": 3
            }
          ]
        },
        {
          "id": "9e375d51-cc73-4164-964b-09c34172981a",
          "status-id": "4e304316-386d-3409-af2e-78857eec5cfe",
          "artist-credit-id": "7403167d-416b-3dee-96c6-4725d8c3eed3",
          "count": 1,
          "title": "Reload",
          "status": "Official",
          "artist-credit": [
            {
              "name": "Metallica",
              "artist": {
                "id": "65f4f0c5-ef9e-490c-aee3-909e7ae6b2ab",
                "name": "Metallica",
                "sort-name": "Metallica"
              }
            }
          ],
          "release-group": {
            "id": "8fd32554-02a7-3788-a761-7012e0e75e55",
            "type-id": "f529b476-6e62-324f-b0aa-1f3e33d313fc",
            "primary-type-id": "f529b476-6e62-324f-b0aa-1f3e33d313fc",
            "title": "Reload",
            "primary-type": "Album"
          },
          "date": "1997-11-18",
          "country": "US",
          "release-events": [
            {
              "date": "1997-11-18",
              "area": {
                "id": "489ce91b-6658-3307-9877-795b68554c98",
                "name": "United States",
                "sort-name": "United States",
                "iso-3166-1-codes": [
                  "US"
                ]
              }
            }
          ],
          "track-count": 13,
          "media": [
            {
              "id": "a39c5253-38d4-3fe1-96b4-538fe7aa344a",
              "position": 1,
              "format": "CD",
              "track": [
                {
                  "id": "8d55e292-fb62-37ae-b3ad-dcefa6733d5e",
                  "number": "11",
                  "title": "Low Man\u2019s Lyric",
                  "length": 457400
                }
              ],
              "track-count": 13,
              "track-offset": 10
            }
          ]
        },
        {
          "id": "ebc04d60-98ea-4d02-832e-cc0460397b3a",
          "status-id": "1156806e-d06a-38bd-83f0-cf2284a808b9",
          "artist-credit-id": "949a7fd5-fe73-3e8f-922e-01ff4ca958f7",
          "count": 1,
          "title": "The Metal Museum \u2013 Metallised Hearts 3",
          "status": "Bootleg",
          "artist-credit": [
            {
              "name": "Various Artists",
              "artist": {
                "id": "89ad4ac3-39f7-470e-963a-56509c546377",
                "name": "Various Artists",
                "sort-name": "Various Artists",
                "disambiguation": "add compilations to this artist"
              }
            }
          ],
          "release-group": {
            "id": "d10430c1-f760-4a43-a194-9766a1a18383",
            "type-id": "dd2a21e1-0c00-3729-a7a0-de60b84eb5d1",
            "primary-type-id": "f529b476-6e62-324f-b0aa-1f3e33d313fc",
            "title": "The Metal Museum \u2013 Metallised Hearts 3",
            "primary-type": "Album",
            "secondary-types": [
              "Compilation"
            ],
            "secondary-type-ids": [
              "dd2a21e1-0c00-3729-a7a0-de60b84eb5d1"
            ]
          },
          "date": "",
          "country": "XW",
          "release-events": [
            {
              "date": "",
              "area": {
                "id": "525d4e18-3d00-31b9-a58b-a146a916de8f",
                "name": "[Worldwide]",
                "sort-name": "[Worldwide]",
                "iso-3166-1-codes": [
                  "XW"
                ]
              }
            }
          ],
          "track-count": 14,
          "media": [
            {
              "id": "ef61fcf2-04f9-3176-b3e5-df891ebe5021",
              "position": 1,
              "format": "Digital Media",
              "track": [
                {
                  "id": "0ca4ee6d-7833-3921-812d-a71c1308c126",
                  "number": "3",
                  "title": "Low Man\u2019s Lyric",
                  "length": 458199
                }
              ],
              "track-count": 14,
              "track-offset": 2
            }
          ]
        },
        {
          "id": "1a5c2e08-0a96-36b5-ad96-0243aa716f8e",
          "status-id": "4e304316-386d-3409-af2e-78857eec5cfe",
          "artist-credit-id": "7403167d-416b-3dee-96c6-4725d8c3eed3",
          "count": 1,
          "title": "Reload",
          "status": "Official",
          "artist-credit": [
            {
              "name": "Metallica",
              "artist": {
                "id": "65f4f0c5-ef9e-490c-aee3-909e7ae6b2ab",
                "name": "Metallica",
                "sort-name": "Metallica"
              }
            }
          ],
          "release-group": {
            "id": "8fd32554-02a7-3788-a761-7012e0e75e55",
            "type-id": "f529b476-6e62-324f-b0aa-1f3e33d313fc",
            "primary-type-id": "f529b476-6e62-324f-b0aa-1f3e33d313fc",
            "title": "Reload",
            "primary-type": "Album"
          },
          "date": "1997-11-18",
          "country": "XE",
          "release-events": [
            {
              "date": "1997-11-18",
              "area": {
                "id": "89a675c2-3e37-3518-b83c-418bad59a85a",
                "name": "Europe",
                "sort-name": "Europe",
                "iso-3166-1-codes": [
                  "XE"
                ]
              }
            }
          ],
          "track-count": 13,
          "media": [
            {
              "id": "661e6952-71a1-38cd-853b-90b25e11fdce",
              "position": 1,
              "format": "CD",
              "track": [
                {
                  "id": "0f10bbd2-c919-3d06-88b5-4755b3d577b6",
                  "number": "11",
                  "title": "Low Man\u2019s Lyric",
                  "length": 457400
                }
              ],
              "track-count": 13,
              "track-offset": 10
            }
          ]
        },
        {
          "id": "b93dd30c-f94b-49c9-b3c1-69298cea52c2",
          "status-id": "4e304316-386d-3409-af2e-78857eec5cfe",
          "artist-credit-id": "7403167d-416b-3dee-96c6-4725d8c3eed3",
          "count": 2,
          "title": "Reload",
          "status": "Official",
          "artist-credit": [
            {
              "name": "Metallica",
              "artist": {
                "id": "65f4f0c5-ef9e-490c-aee3-909e7ae6b2ab",
                "name": "Metallica",
                "sort-name": "Metallica"
              }
            }
          ],
          "release-group": {
            "id": "8fd32554-02a7-3788-a761-7012e0e75e55",
            "type-id": "f529b476-6e62-324f-b0aa-1f3e33d313fc",
            "primary-type-id": "f529b476-6e62-324f-b0aa-1f3e33d313fc",
            "title": "Reload",
            "primary-type": "Album"
          },
          "date": "1997-11-18",
          "country": "US",
          "release-events": [
            {
              "date": "1997-11-18",
              "area": {
                "id": "489ce91b-6658-3307-9877-795b68554c98",
                "name": "United States",
                "sort-name": "United States",
                "iso-3166-1-codes": [
                  "US"
                ]
              }
            }
          ],
          "track-count": 13,
          "media": [
            {
              "id": "a399b538-4d8b-360a-883b-90c8f3c5a3ad",
              "position": 2,
              "format": "12\" Vinyl",
              "track": [
                {
                  "id": "e3db918a-23c6-3339-9e1b-33de8b0b10b0",
                  "number": "D1",
                  "title": "Low Man\u2019s Lyric",
                  "length": 456000
                }
              ],
              "track-count": 6,
              "track-offset": 3
            }
          ]
        },
        {
          "id": "2705207c-2306-4825-a0a7-d933837930bf",
          "status-id": "4e304316-386d-3409-af2e-78857eec5cfe",
          "artist-credit-id": "7403167d-416b-3dee-96c6-4725d8c3eed3",
          "count": 1,
          "title": "Reload",
          "status": "Official",
          "artist-credit": [
            {
              "name": "Metallica",
              "artist": {
                "id": "65f4f0c5-ef9e-490c-aee3-909e7ae6b2ab",
                "name": "Metallica",
                "sort-name": "Metallica"
              }
            }
          ],
          "release-group": {
            "id": "8fd32554-02a7-3788-a761-7012e0e75e55",
            "type-id": "f529b476-6e62-324f-b0aa-1f3e33d313fc",
            "primary-type-id": "f529b476-6e62-324f-b0aa-1f3e33d313fc",
            "title": "Reload",
            "primary-type": "Album"
          },
          "date": "2016",
          "country": "XW",
          "release-events": [
            {
              "date": "2016",
              "area": {
                "id": "525d4e18-3d00-31b9-a58b-a146a916de8f",
                "name": "[Worldwide]",
                "sort-name": "[Worldwide]",
                "iso-3166-1-codes": [
                  "XW"
                ]
              }
            }
          ],
          "track-count": 13,
          "media": [
            {
              "id": "fc9d7d2b-d26c-3c56-9753-5b8fc27a657f",
              "position": 1,
              "format": "Digital Media",
              "track": [
                {
                  "id": "5c021fd1-b2da-48a8-bcb4-ecd06a5a255d",
                  "number": "11",
                  "title": "Low Man\u2019s Lyric",
                  "length": 457400
                }
              ],
              "track-count": 13,
              "track-offset": 10
            }
          ]
        }
      ],
      "isrcs": [
        "GBAMC9700010",
        "USEV19719683"
      ],
      "tags": [
        {
          "count": 6,
          "name": "alternative rock"
        },
        {
          "count": 1,
          "name": "heavy metal"
        },
        {
          "count": 1,
          "name": "hard rock"
        },
        {
          "count": 1,
          "name": "speed metal"
        },
        {
          "count": 1,
          "name": "pop/rock"
        }
      ]
    },
    {
      "id": "7bcfaea7-96bd-4fed-bbbc-28f351ff7081",
      "score": 100,
      "artist-credit-id": "7403167d-416b-3dee-96c6-4725d8c3eed3",
      "title": "Low Man's Lyric",
      "length": 419760,
      "video": null,
      "artist-credit": [
        {
          "name": "Metallica",
          "artist": {
            "id": "65f4f0c5-ef9e-490c-aee3-909e7ae6b2ab",
            "name": "Metallica",
            "sort-name": "Metallica",
            "aliases": [
              {
                "sort-name": "\u30e1\u30bf\u30ea\u30ab",
                "type-id": "894afba6-2816-3c24-8072-eadb66bd04bc",
                "name": "\u30e1\u30bf\u30ea\u30ab",
                "locale": "ja",
                "type": "Artist name",
                "primary": true,
                "begin-date": null,
                "end-date": null
              },
              {
                "sort-name": "Metalica",
                "type-id": "1937e404-b981-3cb7-8151-4c86ebfc8d8e",
                "name": "Metalica",
                "locale": null,
                "type": "Search hint",
                "primary": null,
                "begin-date": null,
                "end-date": null
              },
              {
                "sort-name": "\uba54\ud0c8\ub9ac\uce74",
                "name": "\uba54\ud0c8\ub9ac\uce74",
                "locale": "ko_KR",
                "type": null,
                "primary": true,
                "begin-date": null,
                "end-date": null
              },
              {
                "sort-name": "Metallica",
                "type-id": "894afba6-2816-3c24-8072-eadb66bd04bc",
                "name": "Metallica",
                "locale": "en",
                "type": "Artist name",
                "primary": true,
                "begin-date": null,
                "end-date": null
              }
            ]
          }
        }
      ],
      "releases": [
        {
          "id": "80883868-16f7-4be2-8a83-fb75a57032d0",
          "status-id": "1156806e-d06a-38bd-83f0-cf2284a808b9",
          "artist-credit-id": "7403167d-416b-3dee-96c6-4725d8c3eed3",
          "count": 1,
          "title": "Best Ballads",
          "status": "Bootleg",
          "artist-credit": [
            {
              "name": "Metallica",
              "artist": {
                "id": "65f4f0c5-ef9e-490c-aee3-909e7ae6b2ab",
                "name": "Metallica",
                "sort-name": "Metallica"
              }
            }
          ],
          "release-group": {
            "id": "d4b6ff9a-0e99-386c-84c5-ec41e4514a93",
            "type-id": "dd2a21e1-0c00-3729-a7a0-de60b84eb5d1",
            "primary-type-id": "f529b476-6e62-324f-b0aa-1f3e33d313fc",
            "title": "Best Ballads",
            "primary-type": "Album",
            "secondary-types": [
              "Compilation"
            ],
            "secondary-type-ids": [
              "dd2a21e1-0c00-3729-a7a0-de60b84eb5d1"
            ]
          },
          "track-count": 10,
          "media": [
            {
              "id": "40ec28d1-27ee-3abf-8e08-b8dde30ea1ec",
              "position": 1,
              "track": [
                {
                  "id": "54d70f51-656a-3657-8320-742fd12d7b32",
                  "number": "2",
                  "title": "Low Man's Lyric",
                  "length": 419760
                }
              ],
              "track-count": 10,
              "track-offset": 1
            }
          ]
        }
      ]
    },
    {
      "id": "d116da5a-4af3-43b1-b8f9-c32b93079f64",
      "score": 100,
      "artist-credit-id": "7403167d-416b-3dee-96c6-4725d8c3eed3",
      "title": "Low Man's Lyric",
      "length": 426693,
      "disambiguation": "live, 1997-12-18: Acoustica: KSJO Studio, San Jose, CA, USA",
      "video": null,
      "artist-credit": [
        {
          "name": "Metallica",
          "artist": {
            "id": "65f4f0c5-ef9e-490c-aee3-909e7ae6b2ab",
            "name": "Metallica",
            "sort-name": "Metallica",
            "aliases": [
              {
                "sort-name": "\u30e1\u30bf\u30ea\u30ab",
                "type-id": "894afba6-2816-3c24-8072-eadb66bd04bc",
                "name": "\u30e1\u30bf\u30ea\u30ab",
                "locale": "ja",
                "type": "Artist name",
                "primary": true,
                "begin-date": null,
                "end-date": null
              },
              {
                "sort-name": "Metalica",
                "type-id": "1937e404-b981-3cb7-8151-4c86ebfc8d8e",
                "name": "Metalica",
                "locale": null,
                "type": "Search hint",
                "primary": null,
                "begin-date": null,
                "end-date": null
              },
              {
                "sort-name": "\uba54\ud0c8\ub9ac\uce74",
                "name": "\uba54\ud0c8\ub9ac\uce74",
                "locale": "ko_KR",
                "type": null,
                "primary": true,
                "begin-date": null,
                "end-date": null
              },
              {
                "sort-name": "Metallica",
                "type-id": "894afba6-2816-3c24-8072-eadb66bd04bc",
                "name": "Metallica",
                "locale": "en",
                "type": "Artist name",
                "primary": true,
                "begin-date": null,
                "end-date": null
              }
            ]
          }
        }
      ],
      "first-release-date": "1998",
      "releases": [
        {
          "id": "c2dee52c-7c0e-44d4-ab5f-9740d46dd846",
          "status-id": "1156806e-d06a-38bd-83f0-cf2284a808b9",
          "artist-credit-id": "7403167d-416b-3dee-96c6-4725d8c3eed3",
          "count": 1,
          "title": "1997-12-18: Acoustica: KSJO Studio, San Jose, CA, USA",
          "status": "Bootleg",
          "artist-credit": [
            {
              "name": "Metallica",
              "artist": {
                "id": "65f4f0c5-ef9e-490c-aee3-909e7ae6b2ab",
                "name": "Metallica",
                "sort-name": "Metallica"
              }
            }
          ],
          "release-group": {
            "id": "e313feb3-2e3d-3e65-9b94-6a45fedf67c2",
            "type-id": "6fd474e2-6b58-3102-9d17-d6f7eb7da0a0",
            "primary-type-id": "f529b476-6e62-324f-b0aa-1f3e33d313fc",
            "title": "1997-12-18: Acoustica: KSJO Studio, San Jose, CA, USA",
            "primary-type": "Album",
            "secondary-types": [
              "Live"
            ],
            "secondary-type-ids": [
              "6fd474e2-6b58-3102-9d17-d6f7eb7da0a0"
            ]
          },
          "date": "1998",
          "country": "US",
          "release-events": [
            {
              "date": "1998",
              "area": {
                "id": "489ce91b-6658-3307-9877-795b68554c98",
                "name": "United States",
                "sort-name": "United States",
                "iso-3166-1-codes": [
                  "US"
                ]
              }
            }
          ],
          "track-count": 19,
          "media": [
            {
              "id": "726bfab0-a452-3b7d-8a84-14e667bb0021",
              "position": 1,
              "format": "CD",
              "track": [
                {
                  "id": "7092d566-e16b-393f-8965-5fd47aac0e5d",
                  "number": "2",
                  "title": "Low Man's Lyric",
                  "length": 426693
                }
              ],
              "track-count": 19,
              "track-offset": 1
            }
          ]
        }
      ]
    },
    {
      "id": "8d4a6554-fbdc-45b6-9465-c5d770cf5414",
      "score": 100,
      "artist-credit-id": "7403167d-416b-3dee-96c6-4725d8c3eed3",
      "title": "Low Man's Lyric",
      "length": 417373,
      "video": null,
      "artist-credit": [
        {
          "name": "Metallica",
          "artist": {
            "id": "65f4f0c5-ef9e-490c-aee3-909e7ae6b2ab",
            "name": "Metallica",
            "sort-name": "Metallica",
            "aliases": [
              {
                "sort-name": "\u30e1\u30bf\u30ea\u30ab",
                "type-id": "894afba6-2816-3c24-8072-eadb66bd04bc",
                "name": "\u30e1\u30bf\u30ea\u30ab",
                "locale": "ja",
                "type": "Artist name",
                "primary": true,
                "begin-date": null,
                "end-date": null
              },
              {
                "sort-name": "Metalica",
                "type-id": "1937e404-b981-3cb7-8151-4c86ebfc8d8e",
                "name": "Metalica",
                "locale": null,
                "type": "Search hint",
                "primary": null,
                "begin-date": null,
                "end-date": null
              },
              {
                "sort-name": "\uba54\ud0c8\ub9ac\uce74",
                "name": "\uba54\ud0c8\ub9ac\uce74",
                "locale": "ko_KR",
                "type": null,
                "primary": true,
                "begin-date": null,
                "end-date": null
              },
              {
                "sort-name": "Metallica",
                "type-id": "894afba6-2816-3c24-8072-eadb66bd04bc",
                "name": "Metallica",
                "locale": "en",
                "type": "Artist name",
                "primary": true,
                "begin-date": null,
                "end-date": null
              }
            ]
          }
        }
      ],
      "first-release-date": "2000",
      "releases": [
        {
          "id": "fec2c8e3-16e8-4835-a3a6-74d14bdc3eaa",
          "status-id": "1156806e-d06a-38bd-83f0-cf2284a808b9",
          "artist-credit-id": "7403167d-416b-3dee-96c6-4725d8c3eed3",
          "count": 1,
          "title": "Platinum Collection'2000",
          "status": "Bootleg",
          "artist-credit": [
            {
              "name": "Metallica",
              "artist": {
                "id": "65f4f0c5-ef9e-490c-aee3-909e7ae6b2ab",
                "name": "Metallica",
                "sort-name": "Metallica"
              }
            }
          ],
          "release-group": {
            "id": "2dd6b508-4019-4a91-885d-05133a8dfdf0",
            "type-id": "dd2a21e1-0c00-3729-a7a0-de60b84eb5d1",
            "primary-type-id": "f529b476-6e62-324f-b0aa-1f3e33d313fc",
            "title": "Platinum Collection'2000",
            "primary-type": "Album",
            "secondary-types": [
              "Compilation"
            ],
            "secondary-type-ids": [
              "dd2a21e1-0c00-3729-a7a0-de60b84eb5d1"
            ]
          },
          "date": "2000",
          "country": "RU",
          "release-events": [
            {
              "date": "2000",
              "area": {
                "id": "1f1fc3a4-9500-39b8-9f10-f0a465557eef",
                "name": "Russia",
                "sort-name": "Russia",
                "iso-3166-1-codes": [
                  "RU"
                ]
              }
            }
          ],
          "track-count": 13,
          "media": [
            {
              "id": "74ec58a9-898d-3368-b58b-9bbb16cdbed1",
              "position": 1,
              "track": [
                {
                  "id": "8486eef3-32e1-314c-9dc1-d1259ac181d4",
                  "number": "12",
                  "title": "Low Man's Lyric",
                  "length": 417373
                }
              ],
              "track-count": 13,
              "track-offset": 11
            }
          ]
        }
      ]
    },
    {
      "id": "b38a1c61-9dac-42c0-a210-2e7292b6b1ad",
      "score": 100,
      "artist-credit-id": "7403167d-416b-3dee-96c6-4725d8c3eed3",
      "title": "Low Man's Lyric",
      "length": 440440,
      "video": null,
      "artist-credit": [
        {
          "name": "Metallica",
          "artist": {
            "id": "65f4f0c5-ef9e-490c-aee3-909e7ae6b2ab",
            "name": "Metallica",
            "sort-name": "Metallica",
            "aliases": [
              {
                "sort-name": "\u30e1\u30bf\u30ea\u30ab",
                "type-id": "894afba6-2816-3c24-8072-eadb66bd04bc",
                "name": "\u30e1\u30bf\u30ea\u30ab",
                "locale": "ja",
                "type": "Artist name",
                "primary": true,
                "begin-date": null,
                "end-date": null
              },
              {
                "sort-name": "Metalica",
                "type-id": "1937e404-b981-3cb7-8151-4c86ebfc8d8e",
                "name": "Metalica",
                "locale": null,
                "type": "Search hint",
                "primary": null,
                "begin-date": null,
                "end-date": null
              },
              {
                "sort-name": "\uba54\ud0c8\ub9ac\uce74",
                "name": "\uba54\ud0c8\ub9ac\uce74",
                "locale": "ko_KR",
                "type": null,
                "primary": true,
                "begin-date": null,
                "end-date": null
              },
              {
                "sort-name": "Metallica",
                "type-id": "894afba6-2816-3c24-8072-eadb66bd04bc",
                "name": "Metallica",
                "locale": "en",
                "type": "Artist name",
                "primary": true,
                "begin-date": null,
                "end-date": null
              }
            ]
          }
        }
      ],
      "first-release-date": "2006",
      "releases": [
        {
          "id": "db76d47d-ef63-46b4-bc01-74d7f54a4b88",
          "status-id": "1156806e-d06a-38bd-83f0-cf2284a808b9",
          "artist-credit-id": "7403167d-416b-3dee-96c6-4725d8c3eed3",
          "count": 1,
          "title": "The Golden Unplugged Album",
          "status": "Bootleg",
          "artist-credit": [
            {
              "name": "Metallica",
              "artist": {
                "id": "65f4f0c5-ef9e-490c-aee3-909e7ae6b2ab",
                "name": "Metallica",
                "sort-name": "Metallica"
              }
            }
          ],
          "release-group": {
            "id": "065a6793-3676-3f76-ada7-476efde321f2",
            "type-id": "dd2a21e1-0c00-3729-a7a0-de60b84eb5d1",
            "primary-type-id": "f529b476-6e62-324f-b0aa-1f3e33d313fc",
            "title": "The Golden Unplugged Album",
            "primary-type": "Album",
            "secondary-types": [
              "Compilation"
            ],
            "secondary-type-ids": [
              "dd2a21e1-0c00-3729-a7a0-de60b84eb5d1"
            ]
          },
          "track-count": 13,
          "media": [
            {
              "id": "611482a7-a8bb-3800-8052-4344a8cfaf3a",
              "position": 1,
              "track": [
                {
                  "id": "77784cba-067f-301f-9383-b813a7e77982",
                  "number": "10",
                  "title": "Low Man's Lyric",
                  "length": 440440
                }
              ],
              "track-count": 13,
              "track-offset": 9
            }
          ]
        }
      ],
      "tags": [
        {
          "count": 1,
          "name": "heavy metal"
        },
        {
          "count": 1,
          "name": "thrash metal"
        },
        {
          "count": 2,
          "name": "metal"
        },
        {
          "count": 1,
          "name": "hard rock"
        }
      ]
    }
  ]
}