{
  "page": 1,
  "results": [
    {
      "adult": false,
      "backdrop_path": "/ntPgSYKwPg9xKO4VvLJYfInSyZa.jpg",
      "id": 308014,
      "name": "Berlin and the Lady with an Ermine",
      "original_name": "Berl\u00edn y la dama del armi\u00f1o",
      "overview": "Hungry for a new heist, Berlin summons the gang to Seville and turns an ambitious duke into the victim of his own plan: to steal a da Vinci masterpiece.",
      "poster_path": "/kru9Y5uRXdZFcUyeRlcv4bP4hOr.jpg",
      "media_type": "tv",
      "original_language": "es",
      "genre_ids": [
        18,
        80
      ],
      "popularity": 202.4855,
      "first_air_date": "2026-05-15",
      "softcore": false,
      "vote_average": 7.6,
      "vote_count": 30,
      "origin_country": [
        "ES"
      ]
    },
    {
      "adult": false,
      "backdrop_path": "/bq28ajZaoMyzEIm6REelqyqtEDZ.jpg",
      "id": 76479,
      "name": "The Boys",
      "original_name": "The Boys",
      "overview": "A group of vigilantes known informally as \u201cThe Boys\u201d set out to take down corrupt superheroes with no more than blue-collar grit and a willingness to fight dirty.",
      "poster_path": "/in1R2dDc421JxsoRWaIIAqVI2KE.jpg",
      "media_type": "tv",
      "original_language": "en",
      "genre_ids": [
        10765,
        10759
      ],
      "popularity": 607.1081,
      "first_air_date": "2019-07-25",
      "softcore": false,
      "vote_average": 8.46,
      "vote_count": 12382,
      "origin_country": [
        "US"
      ]
    },
    {
      "adult": false,
      "backdrop_path": "/cdD0InWMH4e6AxceQs93fQRYsfO.jpg",
      "id": 273240,
      "name": "Off Campus",
      "original_name": "Off Campus",
      "overview": "Hannah Wells tutors hockey captain Garrett Graham to win over her crush. Their deal becomes real connection as they face their pasts. Friends Logan, Dean, Tucker, and Allie navigate college life and love.",
      "poster_path": "/gtoV2udbEnUgkMuCNX8zJrEwm7N.jpg",
      "media_type": "tv",
      "original_language": "en",
      "genre_ids": [
        18
      ],
      "popularity": 242.6623,
      "first_air_date": "2026-05-13",
      "softcore": false,
      "vote_average": 8.845,
      "vote_count": 97,
      "origin_country": [
        "US"
      ]
    },
    {
      "adult": false,
      "backdrop_path": "/dQCKc5NKeKOGAQusk2FdctGB9k5.jpg",
      "id": 71915,
      "name": "Good Omens",
      "original_name": "Good Omens",
      "overview": "Aziraphale and Crowley, of Heaven and Hell respectively, have grown rather fond of the Earth. So it's terrible news that it's about to end. The armies of Good and Evil are amassing. The Four Horsemen are ready to ride. Everything is going according to the Divine Plan...except that someone seems to have misplaced the Antichrist. Can our heroes find him and stop Armageddon before it's too late?",
      "poster_path": "/nO68XVx5of8hlBwEOGOkPC8Mveu.jpg",
      "media_type": "tv",
      "original_language": "en",
      "genre_ids": [
        35,
        18,
        10765
      ],
      "popularity": 54.1911,
      "first_air_date": "2019-05-31",
      "softcore": false,
      "vote_average": 8.026,
      "vote_count": 2300,
      "origin_country": [
        "GB"
      ]
    },
    {
      "adult": false,
      "backdrop_path": "/auyEi4Xho43HFvVQnd42LzqBdiV.jpg",
      "id": 124364,
      "name": "FROM",
      "original_name": "FROM",
      "overview": "Unravel the mystery of a nightmarish town in middle America that traps all those who enter. As the unwilling residents fight to keep a sense of normalcy and search for a way out, they must also survive the threats of the surrounding forest \u2013 including the terrifying creatures that come out when the sun goes down.",
      "poster_path": "/pRtJagIxpfODzzb0T0NAvZSzErC.jpg",
      "media_type": "tv",
      "original_language": "en",
      "genre_ids": [
        9648,
        18,
        10765
      ],
      "popularity": 629.4514,
      "first_air_date": "2022-02-20",
      "softcore": false,
      "vote_average": 8.36,
      "vote_count": 3172,
      "origin_country": [
        "US"
      ]
    },
    {
      "adult": false,
      "backdrop_path": "/ewlmL0nxo2lLqBj69upgp2gjHpV.jpg",
      "id": 299167,
      "name": "Dutton Ranch",
      "original_name": "Dutton Ranch",
      "overview": "Rip Wheeler and Beth Dutton gamble everything on a new life in South Texas, but the promise of building a future far from the ghosts of Yellowstone quickly collides with brutal new realities and a rival ranch that will stop at nothing to protect its empire.",
      "poster_path": "/xsiecCxd8lkcAluw0wWwbW5CwSv.jpg",
      "media_type": "tv",
      "original_language": "en",
      "genre_ids": [
        37,
        18
      ],
      "popularity": 116.48,
      "first_air_date": "2026-05-15",
      "softcore": false,
      "vote_average": 9.241,
      "vote_count": 27,
      "origin_country": [
        "US"
      ]
    },
    {
      "adult": false,
      "backdrop_path": "/mez2Z3WqlPKNXpi7mWoiiE5guE9.jpg",
      "id": 85552,
      "name": "Euphoria",
      "original_name": "Euphoria",
      "overview": "A group of high school students navigate love and friendships in a world of drugs, sex, trauma, and social media.",
      "poster_path": "/aJrG7OkoTMPWG5c8opz8a93AZPY.jpg",
      "media_type": "tv",
      "original_language": "en",
      "genre_ids": [
        18
      ],
      "popularity": 226.3294,
      "first_air_date": "2019-06-16",
      "softcore": false,
      "vote_average": 8.287,
      "vote_count": 10637,
      "origin_country": [
        "US"
      ]
    },
    {
      "adult": false,
      "backdrop_path": "/nLyXXIDMpDHvUgxchezxuhoJ4Ej.jpg",
      "id": 235930,
      "name": "Devil May Cry",
      "original_name": "Devil May Cry",
      "overview": "In this epic battle of good vs. evil, the lines are blurry as hell. But a devilishly handsome demon hunter could be the world's best hope for salvation.",
      "poster_path": "/mX9tqfpjqwreONJHhap7SnSSowe.jpg",
      "media_type": "tv",
      "original_language": "en",
      "genre_ids": [
        16,
        10759,
        10765
      ],
      "popularity": 107.5867,
      "first_air_date": "2025-04-03",
      "softcore": false,
      "vote_average": 8.156,
      "vote_count": 365,
      "origin_country": [
        "US"
      ]
    },
    {
      "adult": false,
      "backdrop_path": "/pxnJeLSBdUikUOrWdNgrK1HQy2u.jpg",
      "id": 285807,
      "name": "Nemesis",
      "original_name": "Nemesis",
      "overview": "A relentless LAPD cop becomes obsessed with taking down the master thief behind a string of daring heists \u2014 and only one can come out on top.",
      "poster_path": "/NY7ZwSMw5PjoJdK2CObqiTj7Bm.jpg",
      "media_type": "tv",
      "original_language": "en",
      "genre_ids": [
        10759,
        18,
        80
      ],
      "popularity": 78.917,
      "first_air_date": "2026-05-14",
      "softcore": false,
      "vote_average": 6.077,
      "vote_count": 26,
      "origin_country": [
        "US"
      ]
    },
    {
      "adult": false,
      "backdrop_path": "/810mXC0xkxXVtoKIPGGVgO9PuLh.jpg",
      "id": 259837,
      "name": "The WONDERfools",
      "original_name": "\uc6d0\ub354\ud480\uc2a4",
      "overview": "A goofy group of townies stumbles into superpowers and fights rising evil as doomsday panic grows in this wild, turn-of-the-century action comedy.",
      "poster_path": "/jj7AYkz2OLRDL1wfJmjTXyWQ5I4.jpg",
      "media_type": "tv",
      "original_language": "ko",
      "genre_ids": [
        10759,
        35,
        10765,
        18
      ],
      "popularity": 157.7488,
      "first_air_date": "2026-05-15",
      "softcore": false,
      "vote_average": 9.3,
      "vote_count": 31,
      "origin_country": [
        "KR"
      ]
    },
    {
      "adult": false,
      "backdrop_path": "/4Mt7WHox67uJ1yErwTBFcV8KWgG.jpg",
      "id": 37854,
      "name": "One Piece",
      "original_name": "\u30ef\u30f3\u30d4\u30fc\u30b9",
      "overview": "Years ago, the fearsome Pirate King, Gol D. Roger was executed leaving a huge pile of treasure and the famous \"One Piece\" behind. Whoever claims the \"One Piece\" will be named the new King of the Pirates.\n\nMonkey D. Luffy, a boy who consumed a \"Devil Fruit,\" decides to follow in the footsteps of his idol, the pirate Shanks, and find the One Piece. It helps, of course, that his body has the properties of rubber and that he's surrounded by a bevy of skilled fighters and thieves to help him along the way.\n\nLuffy will do anything to get the One Piece and become King of the Pirates!",
      "poster_path": "/dB4EDhre2dsC2kxYDavyKWqLQwi.jpg",
      "media_type": "tv",
      "original_language": "ja",
      "genre_ids": [
        10759,
        35,
        16
      ],
      "popularity": 63.0128,
      "first_air_date": "1999-10-20",
      "softcore": false,
      "vote_average": 8.733,
      "vote_count": 5291,
      "origin_country": [
        "JP"
      ]
    },
    {
      "adult": false,
      "backdrop_path": "/x6y59dJBE1o0r4YRsWVQXE2nnlB.jpg",
      "id": 65942,
      "name": "Re:ZERO -Starting Life in Another World-",
      "original_name": "Re:\u30bc\u30ed\u304b\u3089\u59cb\u3081\u308b\u7570\u4e16\u754c\u751f\u6d3b",
      "overview": "Natsuki Subaru, an ordinary high school  student, is on his way home from the convenience store when he finds  himself transported to another world. As he's lost and confused in a new  world where he doesn't even know left from right, the only person to  reach out to him was a beautiful girl with silver hair. Determined to  repay her somehow for saving him from his own despair, Subaru agrees to  help the girl find something she's looking for.",
      "poster_path": "/5MrRCj7z92YLWMXHeWKp19eJPYv.jpg",
      "media_type": "tv",
      "original_language": "ja",
      "genre_ids": [
        16,
        10759,
        10765,
        9648,
        18
      ],
      "popularity": 65.9129,
      "first_air_date": "2016-04-04",
      "softcore": false,
      "vote_average": 7.9,
      "vote_count": 622,
      "origin_country": [
        "JP"
      ]
    },
    {
      "adult": false,
      "backdrop_path": "/qrTAc0ZtQ859Qu5O8cixJzNJpQs.jpg",
      "id": 202555,
      "name": "Daredevil: Born Again",
      "original_name": "Daredevil: Born Again",
      "overview": "Matt Murdock, a blind lawyer with heightened abilities, is fighting for justice through his bustling law firm, while former mob boss Wilson Fisk pursues his own political endeavors in New York. When their past identities begin to emerge, both men find themselves on an inevitable collision course.",
      "poster_path": "/xDUoAsU8lQHOOoRkFiBuarmACDN.jpg",
      "media_type": "tv",
      "original_language": "en",
      "genre_ids": [
        18,
        10759,
        80
      ],
      "popularity": 81.9159,
      "first_air_date": "2025-03-04",
      "softcore": false,
      "vote_average": 8.154,
      "vote_count": 898,
      "origin_country": [
        "US"
      ]
    },
    {
      "adult": false,
      "backdrop_path": "/eFcPBI0tEnFRiJaNHQ74ZcSNQCg.jpg",
      "id": 272432,
      "name": "Born with Luck",
      "original_name": "\u4f4e\u667a\u5546\u72af\u7f6a",
      "overview": "Zhang Yi'ang, a veteran detective, is sent to Sanjiangkou to investigate a case but soon finds himself caught in a web of crime and corruption. While pursuing a powerful criminal network, he unexpectedly receives help from a group of bungling thieves, who inadvertently aid his mission to unravel the truth behind a murder.",
      "poster_path": "/3t7xGceBAsSzWMuDdUpa6xS0x7p.jpg",
      "media_type": "tv",
      "original_language": "zh",
      "genre_ids": [
        18,
        9648,
        80,
        35
      ],
      "popularity": 39.8267,
      "first_air_date": "2026-05-04",
      "softcore": false,
      "vote_average": 8.0,
      "vote_count": 11,
      "origin_country": [
        "CN"
      ]
    },
    {
      "adult": false,
      "backdrop_path": "/6iNWfGVCEfASDdlNb05TP5nG0ll.jpg",
      "id": 79744,
      "name": "The Rookie",
      "original_name": "The Rookie",
      "overview": "Starting over isn't easy, especially for small-town guy John Nolan who, after a life-altering incident, is pursuing his dream of being an LAPD officer. As the force's oldest rookie, he's met with skepticism from some higher-ups who see him as just a walking midlife crisis.",
      "poster_path": "/70kTz0OmjjZe7zHvIDrq2iKW7PJ.jpg",
      "media_type": "tv",
      "original_language": "en",
      "genre_ids": [
        80,
        18,
        35
      ],
      "popularity": 268.3259,
      "first_air_date": "2018-10-16",
      "softcore": false,
      "vote_average": 8.543,
      "vote_count": 3215,
      "origin_country": [
        "US"
      ]
    },
    {
      "adult": false,
      "backdrop_path": "/6ekykPwvAywJRjFEnUoCFWTO9O3.jpg",
      "id": 278573,
      "name": "Perfect Crown",
      "original_name": "21\uc138\uae30 \ub300\uad70\ubd80\uc778",
      "overview": "In 21st-century Korea under a constitutional monarchy, a chaebol heiress with everything but status tries to take control of her future after crossing paths with a lonely prince with nothing but his title. Together, bound by a contract marriage, they begin a class-defying romance to rewrite destiny.",
      "poster_path": "/hpKIZO05WwgAWQlv2VcpqZtg6ap.jpg",
      "media_type": "tv",
      "original_language": "ko",
      "genre_ids": [
        35,
        18
      ],
      "popularity": 124.5286,
      "first_air_date": "2026-04-10",
      "softcore": false,
      "vote_average": 7.816,
      "vote_count": 38,
      "origin_country": [
        "KR"
      ]
    },
    {
      "adult": false,
      "backdrop_path": "/9OQ5BIITkJwRJo9JA6AlCfJIGBQ.jpg",
      "id": 87917,
      "name": "For All Mankind",
      "original_name": "For All Mankind",
      "overview": "Explore an aspirational world where NASA and the space program remained a priority and a focal point of our hopes and dreams as told through the lives of NASA astronauts, engineers, and their families.",
      "poster_path": "/JP3DItWMbrrLiKR5AYUfpsNf2b.jpg",
      "media_type": "tv",
      "original_language": "en",
      "genre_ids": [
        18,
        10765,
        10768
      ],
      "popularity": 56.0068,
      "first_air_date": "2019-11-01",
      "softcore": false,
      "vote_average": 7.742,
      "vote_count": 930,
      "origin_country": [
        "US"
      ]
    },
    {
      "adult": false,
      "backdrop_path": "/9qrroces8C6R9aKr08hACNPVXdZ.jpg",
      "id": 95557,
      "name": "INVINCIBLE",
      "original_name": "INVINCIBLE",
      "overview": "Mark Grayson is a normal teenager except for the fact that his father is the most powerful superhero on the planet. Shortly after his seventeenth birthday, Mark begins to develop powers of his own and enters into his father's tutelage.",
      "poster_path": "/4tblBrslcKSifMVZ3TmtT2ukMor.jpg",
      "media_type": "tv",
      "original_language": "en",
      "genre_ids": [
        16,
        18,
        10765,
        10759
      ],
      "popularity": 108.1374,
      "first_air_date": "2021-03-25",
      "softcore": false,
      "vote_average": 8.6,
      "vote_count": 5752,
      "origin_country": [
        "US"
      ]
    },
    {
      "adult": false,
      "backdrop_path": "/nf3Vlxm3C9U1aKUUQHmKFZmxPSc.jpg",
      "id": 56570,
      "name": "Outlander",
      "original_name": "Outlander",
      "overview": "The story of Claire Randall, a married combat nurse from 1945 who is mysteriously swept back in time to 1743, where she is immediately thrown into an unknown world where her life is threatened. When she is forced to marry Jamie, a chivalrous and romantic young Scottish warrior, a passionate affair is ignited that tears Claire's heart between two vastly different men in two irreconcilable lives.",
      "poster_path": "/oftZNfyTVNU7IfOqoGLoT8MGvNs.jpg",
      "media_type": "tv",
      "original_language": "en",
      "genre_ids": [
        18,
        10765
      ],
      "popularity": 140.9368,
      "first_air_date": "2014-08-09",
      "softcore": false,
      "vote_average": 8.186,
      "vote_count": 2853,
      "origin_country": [
        "US"
      ]
    },
    {
      "adult": false,
      "backdrop_path": "/d8LvQj79fgowZkX4NTZaEG3NwsH.jpg",
      "id": 241609,
      "name": "Your Friends & Neighbors",
      "original_name": "Your Friends & Neighbors",
      "overview": "When a financial titan suddenly finds himself divorced and jobless, he starts robbing his wealthy neighbors to stay afloat. Stealing from his own social circle strangely exhilarates him\u2014but he gradually gets tangled in a deadly web.",
      "poster_path": "/lcp63INKEsVHUly9eayx7gEEOcG.jpg",
      "media_type": "tv",
      "original_language": "en",
      "genre_ids": [
        18,
        80
      ],
      "popularity": 42.1695,
      "first_air_date": "2025-04-10",
      "softcore": false,
      "vote_average": 7.623,
      "vote_count": 219,
      "origin_country": [
        "US"
      ]
    }
  ],
  "total_pages": 500,
  "total_results": 10000
}